VHDL/quadrature_decoder/previous_state_register.vhd
library ieee;
use ieee.std_logic_1164.all;

entity previous_state_register is
	port(
		A 			: in std_logic;
		B 			: in std_logic;
		prev_state 	: out std_logic_vector(1 downto 0)
	);
end previous_state_register;

architecture behav_arch of previous_state_register is
begin
	process(A,B)
	begin
		if(B'event) then
			prev_state <= A & B;
		end if;
	end process;
end behav_arch;

VHDL/quadrature_decoder/testbenches/previous_state_register_tb.vhd
library ieee;
use ieee.std_logic_1164.all;

entity previous_state_register_tb is
end previous_state_register_tb;

architecture tb_arch of previous_state_register_tb is

component previous_state_register is
	port(
		A 			: in std_logic;
		B 			: in std_logic;
		prev_state 	: out std_logic_vector(1 downto 0)
	);
end component;

for test_unit : previous_state_register use entity WORK.previous_state_register(behav_arch);

signal in_A, in_B : std_logic := '1';
signal output : std_logic_vector(1 downto 0);
signal clkgen : std_logic := '1';

begin

	test_unit : previous_state_register port map(
		A => in_A,
		B => in_B,
		prev_state => output
	);

	-- CW signal process with T = 20 ns
	in_A <= not in_A after 10 ns;
	clkgen <= not clkgen after 5 ns;
	
	process(clkgen,in_B)
	begin
		if(clkgen'event and clkgen = '0') then
			in_B <= not in_B;
		end if;
	end process;

end tb_arch;

VHDL/quadrature_decoder/previous_state_register.vcd
$date
  Thu Jul  2 15:58:57 2020
$end
$version
  GHDL v0
$end
$timescale
  1 fs
$end
$scope module standard $end
$upscope $end
$scope module std_logic_1164 $end
$upscope $end
$scope module previous_state_register_tb $end
$var reg 1 ! in_a $end
$var reg 1 " in_b $end
$var reg 2 # output[1:0] $end
$var reg 1 $ clkgen $end
$scope module test_unit $end
$var reg 1 % a $end
$var reg 1 & b $end
$var reg 2 ' prev_state[1:0] $end
$upscope $end
$upscope $end
$enddefinitions $end
#0
1!
1"
bUU #
1$
1%
1&
bUU '
#5000000
0"
b10 #
0$
0&
b10 '
#10000000
0!
1$
0%
#15000000
1"
b01 #
0$
1&
b01 '
#20000000
1!
1$
1%
#25000000
0"
b10 #
0$
0&
b10 '
#30000000
0!
1$
0%
#35000000
1"
b01 #
0$
1&
b01 '
#40000000
1!
1$
1%
#45000000
0"
b10 #
0$
0&
b10 '
#50000000
0!
1$
0%
#55000000
1"
b01 #
0$
1&
b01 '
#60000000
1!
1$
1%
#65000000
0"
b10 #
0$
0&
b10 '
#70000000
0!
1$
0%
#75000000
1"
b01 #
0$
1&
b01 '
#80000000
1!
1$
1%
#85000000
0"
b10 #
0$
0&
b10 '
#90000000
0!
1$
0%
#95000000
1"
b01 #
0$
1&
b01 '
#100000000
1!
1$
1%
