VHDL/quadrature_decoder/change_detector.vhd
library ieee;
use ieee.std_logic_1164.all;

entity change_detector is
	port(
		position			: in std_logic_vector(12 downto 0);
		clk					: in std_logic;
		reset 				: in std_logic;
		position_change 	: out std_logic
	);
end change_detector;

architecture two_stage_arch of change_detector is

signal r_reg, r_next : std_logic_vector(position'high downto 0);

begin
	-- Register
	process(reset,clk)
	begin
		if (reset = '1') then
			r_reg <= (others => '0');
		elsif(rising_edge(clk)) then
			r_reg <= r_next;
		end if;
	end process;

	-- Next state logic
	r_next <= position;

	-- Output Logic
	position_change <= '1' when (position /= r_reg) else '0';
end two_stage_arch;

VHDL/quadrature_decoder/testbenches/change_detector_tb.vhd
library ieee;
use ieee.std_logic_1164.all;
use ieee.numeric_std.all;

entity change_detector_tb is
end change_detector_tb;

architecture tb_arch of change_detector_tb is

component change_detector is
	port(
		position			: in std_logic_vector(12 downto 0);
		clk					: in std_logic;
		reset 				: in std_logic;
		position_change 	: out std_logic
	);
end component;

for test_unit : change_detector use entity WORK.change_detector(two_stage_arch);

signal position : std_logic_vector(12 downto 0) := (others => '0');
signal clk : std_logic := '0';
signal reset : std_logic := '1';
signal position_change : std_logic;
	
begin

	test_unit : change_detector port map(
		position 			=> position,
		clk					=> clk,
		reset				=> reset,
		position_change 	=> position_change
	);

	reset <= '0' after 5 ns;
	clk <= not clk after 62.5 ns; -- F = 16MHz

	process
	begin
		wait for 10 us;
		position <= std_logic_vector(signed(position) + 1);
		wait for 10 us;
		position <= std_logic_vector(signed(position) + 2);
		wait for 10 us;
		position <= std_logic_vector(signed(position) - 4);
		wait for 10 us;
		position <= std_logic_vector(signed(position) + 1);
		wait for 10 us;
		position <= (others => 'U');
	end process;

end tb_arch;

VHDL/quadrature_decoder/testbenches/tb_wave_forms_files/change_detector_tb.vcd
$date
  Sun Jul  5 17:50:16 2020
$end
$version
  GHDL v0
$end
$timescale
  1 fs
$end
$scope module standard $end
$upscope $end
$scope module std_logic_1164 $end
$upscope $end
$scope module numeric_std $end
$upscope $end
$scope module change_detector_tb $end
$var reg 13 ! position[12:0] $end
$var reg 1 " clk $end
$var reg 1 # reset $end
$var reg 1 $ position_change $end
$scope module test_unit $end
$var reg 13 % position[12:0] $end
$var reg 1 & clk $end
$var reg 1 ' reset $end
$var reg 1 ( position_change $end
$var reg 13 ) r_reg[12:0] $end
$var reg 13 * r_next[12:0] $end
$upscope $end
$upscope $end
$enddefinitions $end
#0
b0000000000000 !
0"
1#
0$
b0000000000000 %
0&
1'
0(
b0000000000000 )
b0000000000000 *
#5000000
0#
0'
#62500000
1"
1&
#125000000
0"
0&
#187500000
1"
1&
#250000000
0"
0&
#312500000
1"
1&
#375000000
0"
0&
#437500000
1"
1&
#500000000
0"
0&
#562500000
1"
1&
#625000000
0"
0&
#687500000
1"
1&
#750000000
0"
0&
#812500000
1"
1&
#875000000
0"
0&
#937500000
1"
1&
#1000000000
0"
0&
#1062500000
1"
1&
#1125000000
0"
0&
#1187500000
1"
1&
#1250000000
0"
0&
#1312500000
1"
1&
#1375000000
0"
0&
#1437500000
1"
1&
#1500000000
0"
0&
#1562500000
1"
1&
#1625000000
0"
0&
#1687500000
1"
1&
#1750000000
0"
0&
#1812500000
1"
1&
#1875000000
0"
0&
#1937500000
1"
1&
#2000000000
0"
0&
#2062500000
1"
1&
#2125000000
0"
0&
#2187500000
1"
1&
#2250000000
0"
0&
#2312500000
1"
1&
#2375000000
0"
0&
#2437500000
1"
1&
#2500000000
0"
0&
#2562500000
1"
1&
#2625000000
0"
0&
#2687500000
1"
1&
#2750000000
0"
0&
#2812500000
1"
1&
#2875000000
0"
0&
#2937500000
1"
1&
#3000000000
0"
0&
#3062500000
1"
1&
#3125000000
0"
0&
#3187500000
1"
1&
#3250000000
0"
0&
#3312500000
1"
1&
#3375000000
0"
0&
#3437500000
1"
1&
#3500000000
0"
0&
#3562500000
1"
1&
#3625000000
0"
0&
#3687500000
1"
1&
#3750000000
0"
0&
#3812500000
1"
1&
#3875000000
0"
0&
#3937500000
1"
1&
#4000000000
0"
0&
#4062500000
1"
1&
#4125000000
0"
0&
#4187500000
1"
1&
#4250000000
0"
0&
#4312500000
1"
1&
#4375000000
0"
0&
#4437500000
1"
1&
#4500000000
0"
0&
#4562500000
1"
1&
#4625000000
0"
0&
#4687500000
1"
1&
#4750000000
0"
0&
#4812500000
1"
1&
#4875000000
0"
0&
#4937500000
1"
1&
#5000000000
0"
0&
#5062500000
1"
1&
#5125000000
0"
0&
#5187500000
1"
1&
#5250000000
0"
0&
#5312500000
1"
1&
#5375000000
0"
0&
#5437500000
1"
1&
#5500000000
0"
0&
#5562500000
1"
1&
#5625000000
0"
0&
#5687500000
1"
1&
#5750000000
0"
0&
#5812500000
1"
1&
#5875000000
0"
0&
#5937500000
1"
1&
#6000000000
0"
0&
#6062500000
1"
1&
#6125000000
0"
0&
#6187500000
1"
1&
#6250000000
0"
0&
#6312500000
1"
1&
#6375000000
0"
0&
#6437500000
1"
1&
#6500000000
0"
0&
#6562500000
1"
1&
#6625000000
0"
0&
#6687500000
1"
1&
#6750000000
0"
0&
#6812500000
1"
1&
#6875000000
0"
0&
#6937500000
1"
1&
#7000000000
0"
0&
#7062500000
1"
1&
#7125000000
0"
0&
#7187500000
1"
1&
#7250000000
0"
0&
#7312500000
1"
1&
#7375000000
0"
0&
#7437500000
1"
1&
#7500000000
0"
0&
#7562500000
1"
1&
#7625000000
0"
0&
#7687500000
1"
1&
#7750000000
0"
0&
#7812500000
1"
1&
#7875000000
0"
0&
#7937500000
1"
1&
#8000000000
0"
0&
#8062500000
1"
1&
#8125000000
0"
0&
#8187500000
1"
1&
#8250000000
0"
0&
#8312500000
1"
1&
#8375000000
0"
0&
#8437500000
1"
1&
#8500000000
0"
0&
#8562500000
1"
1&
#8625000000
0"
0&
#8687500000
1"
1&
#8750000000
0"
0&
#8812500000
1"
1&
#8875000000
0"
0&
#8937500000
1"
1&
#9000000000
0"
0&
#9062500000
1"
1&
#9125000000
0"
0&
#9187500000
1"
1&
#9250000000
0"
0&
#9312500000
1"
1&
#9375000000
0"
0&
#9437500000
1"
1&
#9500000000
0"
0&
#9562500000
1"
1&
#9625000000
0"
0&
#9687500000
1"
1&
#9750000000
0"
0&
#9812500000
1"
1&
#9875000000
0"
0&
#9937500000
1"
1&
#10000000000
b0000000000001 !
0"
1$
b0000000000001 %
0&
1(
b0000000000001 *
#10062500000
1"
0$
1&
0(
b0000000000001 )
#10125000000
0"
0&
#10187500000
1"
1&
#10250000000
0"
0&
#10312500000
1"
1&
#10375000000
0"
0&
#10437500000
1"
1&
#10500000000
0"
0&
#10562500000
1"
1&
#10625000000
0"
0&
#10687500000
1"
1&
#10750000000
0"
0&
#10812500000
1"
1&
#10875000000
0"
0&
#10937500000
1"
1&
#11000000000
0"
0&
#11062500000
1"
1&
#11125000000
0"
0&
#11187500000
1"
1&
#11250000000
0"
0&
#11312500000
1"
1&
#11375000000
0"
0&
#11437500000
1"
1&
#11500000000
0"
0&
#11562500000
1"
1&
#11625000000
0"
0&
#11687500000
1"
1&
#11750000000
0"
0&
#11812500000
1"
1&
#11875000000
0"
0&
#11937500000
1"
1&
#12000000000
0"
0&
#12062500000
1"
1&
#12125000000
0"
0&
#12187500000
1"
1&
#12250000000
0"
0&
#12312500000
1"
1&
#12375000000
0"
0&
#12437500000
1"
1&
#12500000000
0"
0&
#12562500000
1"
1&
#12625000000
0"
0&
#12687500000
1"
1&
#12750000000
0"
0&
#12812500000
1"
1&
#12875000000
0"
0&
#12937500000
1"
1&
#13000000000
0"
0&
#13062500000
1"
1&
#13125000000
0"
0&
#13187500000
1"
1&
#13250000000
0"
0&
#13312500000
1"
1&
#13375000000
0"
0&
#13437500000
1"
1&
#13500000000
0"
0&
#13562500000
1"
1&
#13625000000
0"
0&
#13687500000
1"
1&
#13750000000
0"
0&
#13812500000
1"
1&
#13875000000
0"
0&
#13937500000
1"
1&
#14000000000
0"
0&
#14062500000
1"
1&
#14125000000
0"
0&
#14187500000
1"
1&
#14250000000
0"
0&
#14312500000
1"
1&
#14375000000
0"
0&
#14437500000
1"
1&
#14500000000
0"
0&
#14562500000
1"
1&
#14625000000
0"
0&
#14687500000
1"
1&
#14750000000
0"
0&
#14812500000
1"
1&
#14875000000
0"
0&
#14937500000
1"
1&
#15000000000
0"
0&
#15062500000
1"
1&
#15125000000
0"
0&
#15187500000
1"
1&
#15250000000
0"
0&
#15312500000
1"
1&
#15375000000
0"
0&
#15437500000
1"
1&
#15500000000
0"
0&
#15562500000
1"
1&
#15625000000
0"
0&
#15687500000
1"
1&
#15750000000
0"
0&
#15812500000
1"
1&
#15875000000
0"
0&
#15937500000
1"
1&
#16000000000
0"
0&
#16062500000
1"
1&
#16125000000
0"
0&
#16187500000
1"
1&
#16250000000
0"
0&
#16312500000
1"
1&
#16375000000
0"
0&
#16437500000
1"
1&
#16500000000
0"
0&
#16562500000
1"
1&
#16625000000
0"
0&
#16687500000
1"
1&
#16750000000
0"
0&
#16812500000
1"
1&
#16875000000
0"
0&
#16937500000
1"
1&
#17000000000
0"
0&
#17062500000
1"
1&
#17125000000
0"
0&
#17187500000
1"
1&
#17250000000
0"
0&
#17312500000
1"
1&
#17375000000
0"
0&
#17437500000
1"
1&
#17500000000
0"
0&
#17562500000
1"
1&
#17625000000
0"
0&
#17687500000
1"
1&
#17750000000
0"
0&
#17812500000
1"
1&
#17875000000
0"
0&
#17937500000
1"
1&
#18000000000
0"
0&
#18062500000
1"
1&
#18125000000
0"
0&
#18187500000
1"
1&
#18250000000
0"
0&
#18312500000
1"
1&
#18375000000
0"
0&
#18437500000
1"
1&
#18500000000
0"
0&
#18562500000
1"
1&
#18625000000
0"
0&
#18687500000
1"
1&
#18750000000
0"
0&
#18812500000
1"
1&
#18875000000
0"
0&
#18937500000
1"
1&
#19000000000
0"
0&
#19062500000
1"
1&
#19125000000
0"
0&
#19187500000
1"
1&
#19250000000
0"
0&
#19312500000
1"
1&
#19375000000
0"
0&
#19437500000
1"
1&
#19500000000
0"
0&
#19562500000
1"
1&
#19625000000
0"
0&
#19687500000
1"
1&
#19750000000
0"
0&
#19812500000
1"
1&
#19875000000
0"
0&
#19937500000
1"
1&
#20000000000
b0000000000011 !
0"
1$
b0000000000011 %
0&
1(
b0000000000011 *
#20062500000
1"
0$
1&
0(
b0000000000011 )
#20125000000
0"
0&
#20187500000
1"
1&
#20250000000
0"
0&
#20312500000
1"
1&
#20375000000
0"
0&
#20437500000
1"
1&
#20500000000
0"
0&
#20562500000
1"
1&
#20625000000
0"
0&
#20687500000
1"
1&
#20750000000
0"
0&
#20812500000
1"
1&
#20875000000
0"
0&
#20937500000
1"
1&
#21000000000
0"
0&
#21062500000
1"
1&
#21125000000
0"
0&
#21187500000
1"
1&
#21250000000
0"
0&
#21312500000
1"
1&
#21375000000
0"
0&
#21437500000
1"
1&
#21500000000
0"
0&
#21562500000
1"
1&
#21625000000
0"
0&
#21687500000
1"
1&
#21750000000
0"
0&
#21812500000
1"
1&
#21875000000
0"
0&
#21937500000
1"
1&
#22000000000
0"
0&
#22062500000
1"
1&
#22125000000
0"
0&
#22187500000
1"
1&
#22250000000
0"
0&
#22312500000
1"
1&
#22375000000
0"
0&
#22437500000
1"
1&
#22500000000
0"
0&
#22562500000
1"
1&
#22625000000
0"
0&
#22687500000
1"
1&
#22750000000
0"
0&
#22812500000
1"
1&
#22875000000
0"
0&
#22937500000
1"
1&
#23000000000
0"
0&
#23062500000
1"
1&
#23125000000
0"
0&
#23187500000
1"
1&
#23250000000
0"
0&
#23312500000
1"
1&
#23375000000
0"
0&
#23437500000
1"
1&
#23500000000
0"
0&
#23562500000
1"
1&
#23625000000
0"
0&
#23687500000
1"
1&
#23750000000
0"
0&
#23812500000
1"
1&
#23875000000
0"
0&
#23937500000
1"
1&
#24000000000
0"
0&
#24062500000
1"
1&
#24125000000
0"
0&
#24187500000
1"
1&
#24250000000
0"
0&
#24312500000
1"
1&
#24375000000
0"
0&
#24437500000
1"
1&
#24500000000
0"
0&
#24562500000
1"
1&
#24625000000
0"
0&
#24687500000
1"
1&
#24750000000
0"
0&
#24812500000
1"
1&
#24875000000
0"
0&
#24937500000
1"
1&
#25000000000
0"
0&
#25062500000
1"
1&
#25125000000
0"
0&
#25187500000
1"
1&
#25250000000
0"
0&
#25312500000
1"
1&
#25375000000
0"
0&
#25437500000
1"
1&
#25500000000
0"
0&
#25562500000
1"
1&
#25625000000
0"
0&
#25687500000
1"
1&
#25750000000
0"
0&
#25812500000
1"
1&
#25875000000
0"
0&
#25937500000
1"
1&
#26000000000
0"
0&
#26062500000
1"
1&
#26125000000
0"
0&
#26187500000
1"
1&
#26250000000
0"
0&
#26312500000
1"
1&
#26375000000
0"
0&
#26437500000
1"
1&
#26500000000
0"
0&
#26562500000
1"
1&
#26625000000
0"
0&
#26687500000
1"
1&
#26750000000
0"
0&
#26812500000
1"
1&
#26875000000
0"
0&
#26937500000
1"
1&
#27000000000
0"
0&
#27062500000
1"
1&
#27125000000
0"
0&
#27187500000
1"
1&
#27250000000
0"
0&
#27312500000
1"
1&
#27375000000
0"
0&
#27437500000
1"
1&
#27500000000
0"
0&
#27562500000
1"
1&
#27625000000
0"
0&
#27687500000
1"
1&
#27750000000
0"
0&
#27812500000
1"
1&
#27875000000
0"
0&
#27937500000
1"
1&
#28000000000
0"
0&
#28062500000
1"
1&
#28125000000
0"
0&
#28187500000
1"
1&
#28250000000
0"
0&
#28312500000
1"
1&
#28375000000
0"
0&
#28437500000
1"
1&
#28500000000
0"
0&
#28562500000
1"
1&
#28625000000
0"
0&
#28687500000
1"
1&
#28750000000
0"
0&
#28812500000
1"
1&
#28875000000
0"
0&
#28937500000
1"
1&
#29000000000
0"
0&
#29062500000
1"
1&
#29125000000
0"
0&
#29187500000
1"
1&
#29250000000
0"
0&
#29312500000
1"
1&
#29375000000
0"
0&
#29437500000
1"
1&
#29500000000
0"
0&
#29562500000
1"
1&
#29625000000
0"
0&
#29687500000
1"
1&
#29750000000
0"
0&
#29812500000
1"
1&
#29875000000
0"
0&
#29937500000
1"
1&
#30000000000
b1111111111111 !
0"
1$
b1111111111111 %
0&
1(
b1111111111111 *
#30062500000
1"
0$
1&
0(
b1111111111111 )
