VHDL/quadrature_decoder/clk_timer.vhd
library ieee;
use ieee.std_logic_1164.all;
use ieee.numeric_std.all;
 
entity clk_timer is
	generic(timer_threshold_cycles : integer);
	port(
	    clk 		: in std_logic;
	    reset		: in std_logic;
	    timer 		: out std_logic
    );
end entity;
 
architecture rtl of clk_timer is
 
    -- Signal for counting clock periods
    signal r_reg, r_next : integer;
 
begin

    -- Register
    process(clk) is
    begin
        if(reset = '1') then
            r_reg <= 0;
        elsif(rising_edge(clk)) then
            r_reg <= r_next;
        end if;
    end process;

    -- Next state logic
    r_next <= 0 when (r_reg = timer_threshold_cycles - 1)
                else r_reg + 1;

    -- Output logic
    timer <= '1' when (r_reg = timer_threshold_cycles - 1)
                else '0';
 
end architecture;

VHDL/quadrature_decoder/testbenches/clk_timer_tb.vhd
library ieee;
use ieee.std_logic_1164.all;
use ieee.numeric_std.all;
 
entity clk_timer_tb is
end entity;
 
architecture tb_arch of clk_timer_tb is

	component clk_timer is
		generic(timer_threshold_cycles : integer);
		port(
		    clk 		: in std_logic;
		    reset		: in std_logic;
		    timer 		: out std_logic
	    );
	end component;
 
    constant ClockFrequencyHz 			: integer := 16000000; -- 16 MHz
    constant ClockPeriod      			: time := 1000 ms / ClockFrequencyHz;
    constant timer_threshold_cycles		: integer := ClockFrequencyHz / 1000; -- Clk cycles per mili-second (10^-3)
 
    signal clk     	: std_logic := '1';
    signal reset    : std_logic := '1';
    signal timer 	: std_logic := '0';
 
begin
 
    -- The Device Under Test (DUT)
    test_unit : entity work.clk_timer(rtl)
    generic map(timer_threshold_cycles => timer_threshold_cycles)
    port map (
        clk     => clk,
        reset   => reset,
        timer 	=> timer
    );
 
    -- Process for generating the clock
    clk <= not clk after ClockPeriod / 2;
 
    -- Testbench sequence
    process is
    begin
        wait until rising_edge(clk);
        wait until rising_edge(clk);
 
        -- Take the DUT out of reset
        reset <= '0';
 
        wait;
    end process;
 
end architecture;

VHDL/quadrature_decoder/testbenches/tb_wave_forms_files/clk_timer_tb.vcd
$date
  Mon Jul  6 13:37:50 2020
$end
$version
  GHDL v0
$end
$timescale
  1 fs
$end
$scope module standard $end
$upscope $end
$scope module std_logic_1164 $end
$upscope $end
$scope module numeric_std $end
$upscope $end
$scope module clk_timer_tb $end
$var reg 1 ! clk $end
$var reg 1 " reset $end
$var reg 1 # timer $end
$scope module test_unit $end
$var reg 1 $ clk $end
$var reg 1 % reset $end
$var reg 1 & timer $end
$var integer 32 ' r_reg $end
$var integer 32 ( r_next $end
$upscope $end
$upscope $end
$enddefinitions $end
#0
1!
1"
0#
1$
1%
0&
b0 '
b1 (
#31250000
0!
0$
#62500000
1!
1$
#93750000
0!
0$
#125000000
1!
0"
1$
0%
#156250000
0!
0$
#187500000
1!
1$
b1 '
b10 (
#218750000
0!
0$
#250000000
1!
1$
b10 '
b11 (
#281250000
0!
0$
#312500000
1!
1$
b11 '
b100 (
#343750000
0!
0$
#375000000
1!
1$
b100 '
b101 (
#406250000
0!
0$
#437500000
1!
1$
b101 '
b110 (
#468750000
0!
0$
#500000000
1!
1$
b110 '
b111 (
#531250000
0!
0$
#562500000
1!
1$
b111 '
b1000 (
#593750000
0!
0$
#625000000
1!
1$
b1000 '
b1001 (
#656250000
0!
0$
#687500000
1!
1$
b1001 '
b1010 (
#718750000
0!
0$
#750000000
1!
1$
b1010 '
b1011 (
#781250000
0!
0$
#812500000
1!
1$
b1011 '
b1100 (
#843750000
0!
0$
#875000000
1!
1$
b1100 '
b1101 (
#906250000
0!
0$
#937500000
1!
1$
b1101 '
b1110 (
#968750000
0!
0$
#1000000000
1!
1$
b1110 '
b1111 (
#1031250000
0!
0$
#1062500000
1!
1$
b1111 '
b10000 (
#1093750000
0!
0$
#1125000000
1!
1$
b10000 '
b10001 (
#1156250000
0!
0$
#1187500000
1!
1$
b10001 '
b10010 (
#1218750000
0!
0$
#1250000000
1!
1$
b10010 '
b10011 (
#1281250000
0!
0$
#1312500000
1!
1$
b10011 '
b10100 (
#1343750000
0!
0$
#1375000000
1!
1$
b10100 '
b10101 (
#1406250000
0!
0$
#1437500000
1!
1$
b10101 '
b10110 (
#1468750000
0!
0$
#1500000000
1!
1$
b10110 '
b10111 (
#1531250000
0!
0$
#1562500000
1!
1$
b10111 '
b11000 (
#1593750000
0!
0$
#1625000000
1!
1$
b11000 '
b11001 (
#1656250000
0!
0$
#1687500000
1!
1$
b11001 '
b11010 (
#1718750000
0!
0$
#1750000000
1!
1$
b11010 '
b11011 (
#1781250000
0!
0$
#1812500000
1!
1$
b11011 '
b11100 (
#1843750000
0!
0$
#1875000000
1!
1$
b11100 '
b11101 (
#1906250000
0!
0$
#1937500000
1!
1$
b11101 '
b11110 (
#1968750000
0!
0$
#2000000000
1!
1$
b11110 '
b11111 (
#2031250000
0!
0$
#2062500000
1!
1$
b11111 '
b100000 (
#2093750000
0!
0$
#2125000000
1!
1$
b100000 '
b100001 (
#2156250000
0!
0$
#2187500000
1!
1$
b100001 '
b100010 (
#2218750000
0!
0$
#2250000000
1!
1$
b100010 '
b100011 (
#2281250000
0!
0$
#2312500000
1!
1$
b100011 '
b100100 (
#2343750000
0!
0$
#2375000000
1!
1$
b100100 '
b100101 (
#2406250000
0!
0$
#2437500000
1!
1$
b100101 '
b100110 (
#2468750000
0!
0$
#2500000000
1!
1$
b100110 '
b100111 (
#2531250000
0!
0$
#2562500000
1!
1$
b100111 '
b101000 (
#2593750000
0!
0$
#2625000000
1!
1$
b101000 '
b101001 (
#2656250000
0!
0$
#2687500000
1!
1$
b101001 '
b101010 (
#2718750000
0!
0$
#2750000000
1!
1$
b101010 '
b101011 (
#2781250000
0!
0$
#2812500000
1!
1$
b101011 '
b101100 (
#2843750000
0!
0$
#2875000000
1!
1$
b101100 '
b101101 (
#2906250000
0!
0$
#2937500000
1!
1$
b101101 '
b101110 (
#2968750000
0!
0$
#3000000000
1!
1$
b101110 '
b101111 (
#3031250000
0!
0$
#3062500000
1!
1$
b101111 '
b110000 (
#3093750000
0!
0$
#3125000000
1!
1$
b110000 '
b110001 (
#3156250000
0!
0$
#3187500000
1!
1$
b110001 '
b110010 (
#3218750000
0!
0$
#3250000000
1!
1$
b110010 '
b110011 (
#3281250000
0!
0$
#3312500000
1!
1$
b110011 '
b110100 (
#3343750000
0!
0$
#3375000000
1!
1$
b110100 '
b110101 (
#3406250000
0!
0$
#3437500000
1!
1$
b110101 '
b110110 (
#3468750000
0!
0$
#3500000000
1!
1$
b110110 '
b110111 (
#3531250000
0!
0$
#3562500000
1!
1$
b110111 '
b111000 (
#3593750000
0!
0$
#3625000000
1!
1$
b111000 '
b111001 (
#3656250000
0!
0$
#3687500000
1!
1$
b111001 '
b111010 (
#3718750000
0!
0$
#3750000000
1!
1$
b111010 '
b111011 (
#3781250000
0!
0$
#3812500000
1!
1$
b111011 '
b111100 (
#3843750000
0!
0$
#3875000000
1!
1$
b111100 '
b111101 (
#3906250000
0!
0$
#3937500000
1!
1$
b111101 '
b111110 (
#3968750000
0!
0$
#4000000000
1!
1$
b111110 '
b111111 (
#4031250000
0!
0$
#4062500000
1!
1$
b111111 '
b1000000 (
#4093750000
0!
0$
#4125000000
1!
1$
b1000000 '
b1000001 (
#4156250000
0!
0$
#4187500000
1!
1$
b1000001 '
b1000010 (
#4218750000
0!
0$
#4250000000
1!
1$
b1000010 '
b1000011 (
#4281250000
0!
0$
#4312500000
1!
1$
b1000011 '
b1000100 (
#4343750000
0!
0$
#4375000000
1!
1$
b1000100 '
b1000101 (
#4406250000
0!
0$
#4437500000
1!
1$
b1000101 '
b1000110 (
#4468750000
0!
0$
#4500000000
1!
1$
b1000110 '
b1000111 (
#4531250000
0!
0$
#4562500000
1!
1$
b1000111 '
b1001000 (
#4593750000
0!
0$
#4625000000
1!
1$
b1001000 '
b1001001 (
#4656250000
0!
0$
#4687500000
1!
1$
b1001001 '
b1001010 (
#4718750000
0!
0$
#4750000000
1!
1$
b1001010 '
b1001011 (
#4781250000
0!
0$
#4812500000
1!
1$
b1001011 '
b1001100 (
#4843750000
0!
0$
#4875000000
1!
1$
b1001100 '
b1001101 (
#4906250000
0!
0$
#4937500000
1!
1$
b1001101 '
b1001110 (
#4968750000
0!
0$
#5000000000
1!
1$
b1001110 '
b1001111 (
#5031250000
0!
0$
#5062500000
1!
1$
b1001111 '
b1010000 (
#5093750000
0!
0$
#5125000000
1!
1$
b1010000 '
b1010001 (
#5156250000
0!
0$
#5187500000
1!
1$
b1010001 '
b1010010 (
#5218750000
0!
0$
#5250000000
1!
1$
b1010010 '
b1010011 (
#5281250000
0!
0$
#5312500000
1!
1$
b1010011 '
b1010100 (
#5343750000
0!
0$
#5375000000
1!
1$
b1010100 '
b1010101 (
#5406250000
0!
0$
#5437500000
1!
1$
b1010101 '
b1010110 (
#5468750000
0!
0$
#5500000000
1!
1$
b1010110 '
b1010111 (
#5531250000
0!
0$
#5562500000
1!
1$
b1010111 '
b1011000 (
#5593750000
0!
0$
#5625000000
1!
1$
b1011000 '
b1011001 (
#5656250000
0!
0$
#5687500000
1!
1$
b1011001 '
b1011010 (
#5718750000
0!
0$
#5750000000
1!
1$
b1011010 '
b1011011 (
#5781250000
0!
0$
#5812500000
1!
1$
b1011011 '
b1011100 (
#5843750000
0!
0$
#5875000000
1!
1$
b1011100 '
b1011101 (
#5906250000
0!
0$
#5937500000
1!
1$
b1011101 '
b1011110 (
#5968750000
0!
0$
#6000000000
1!
1$
b1011110 '
b1011111 (
#6031250000
0!
0$
#6062500000
1!
1$
b1011111 '
b1100000 (
#6093750000
0!
0$
#6125000000
1!
1$
b1100000 '
b1100001 (
#6156250000
0!
0$
#6187500000
1!
1$
b1100001 '
b1100010 (
#6218750000
0!
0$
#6250000000
1!
1$
b1100010 '
b1100011 (
#6281250000
0!
0$
#6312500000
1!
1$
b1100011 '
b1100100 (
#6343750000
0!
0$
#6375000000
1!
1$
b1100100 '
b1100101 (
#6406250000
0!
0$
#6437500000
1!
1$
b1100101 '
b1100110 (
#6468750000
0!
0$
#6500000000
1!
1$
b1100110 '
b1100111 (
#6531250000
0!
0$
#6562500000
1!
1$
b1100111 '
b1101000 (
#6593750000
0!
0$
#6625000000
1!
1$
b1101000 '
b1101001 (
#6656250000
0!
0$
#6687500000
1!
1$
b1101001 '
b1101010 (
#6718750000
0!
0$
#6750000000
1!
1$
b1101010 '
b1101011 (
#6781250000
0!
0$
#6812500000
1!
1$
b1101011 '
b1101100 (
#6843750000
0!
0$
#6875000000
1!
1$
b1101100 '
b1101101 (
#6906250000
0!
0$
#6937500000
1!
1$
b1101101 '
b1101110 (
#6968750000
0!
0$
#7000000000
1!
1$
b1101110 '
b1101111 (
#7031250000
0!
0$
#7062500000
1!
1$
b1101111 '
b1110000 (
#7093750000
0!
0$
#7125000000
1!
1$
b1110000 '
b1110001 (
#7156250000
0!
0$
#7187500000
1!
1$
b1110001 '
b1110010 (
#7218750000
0!
0$
#7250000000
1!
1$
b1110010 '
b1110011 (
#7281250000
0!
0$
#7312500000
1!
1$
b1110011 '
b1110100 (
#7343750000
0!
0$
#7375000000
1!
1$
b1110100 '
b1110101 (
#7406250000
0!
0$
#7437500000
1!
1$
b1110101 '
b1110110 (
#7468750000
0!
0$
#7500000000
1!
1$
b1110110 '
b1110111 (
#7531250000
0!
0$
#7562500000
1!
1$
b1110111 '
b1111000 (
#7593750000
0!
0$
#7625000000
1!
1$
b1111000 '
b1111001 (
#7656250000
0!
0$
#7687500000
1!
1$
b1111001 '
b1111010 (
#7718750000
0!
0$
#7750000000
1!
1$
b1111010 '
b1111011 (
#7781250000
0!
0$
#7812500000
1!
1$
b1111011 '
b1111100 (
#7843750000
0!
0$
#7875000000
1!
1$
b1111100 '
b1111101 (
#7906250000
0!
0$
#7937500000
1!
1$
b1111101 '
b1111110 (
#7968750000
0!
0$
#8000000000
1!
1$
b1111110 '
b1111111 (
#8031250000
0!
0$
#8062500000
1!
1$
b1111111 '
b10000000 (
#8093750000
0!
0$
#8125000000
1!
1$
b10000000 '
b10000001 (
#8156250000
0!
0$
#8187500000
1!
1$
b10000001 '
b10000010 (
#8218750000
0!
0$
#8250000000
1!
1$
b10000010 '
b10000011 (
#8281250000
0!
0$
#8312500000
1!
1$
b10000011 '
b10000100 (
#8343750000
0!
0$
#8375000000
1!
1$
b10000100 '
b10000101 (
#8406250000
0!
0$
#8437500000
1!
1$
b10000101 '
b10000110 (
#8468750000
0!
0$
#8500000000
1!
1$
b10000110 '
b10000111 (
#8531250000
0!
0$
#8562500000
1!
1$
b10000111 '
b10001000 (
#8593750000
0!
0$
#8625000000
1!
1$
b10001000 '
b10001001 (
#8656250000
0!
0$
#8687500000
1!
1$
b10001001 '
b10001010 (
#8718750000
0!
0$
#8750000000
1!
1$
b10001010 '
b10001011 (
#8781250000
0!
0$
#8812500000
1!
1$
b10001011 '
b10001100 (
#8843750000
0!
0$
#8875000000
1!
1$
b10001100 '
b10001101 (
#8906250000
0!
0$
#8937500000
1!
1$
b10001101 '
b10001110 (
#8968750000
0!
0$
#9000000000
1!
1$
b10001110 '
b10001111 (
#9031250000
0!
0$
#9062500000
1!
1$
b10001111 '
b10010000 (
#9093750000
0!
0$
#9125000000
1!
1$
b10010000 '
b10010001 (
#9156250000
0!
0$
#9187500000
1!
1$
b10010001 '
b10010010 (
#9218750000
0!
0$
#9250000000
1!
1$
b10010010 '
b10010011 (
#9281250000
0!
0$
#9312500000
1!
1$
b10010011 '
b10010100 (
#9343750000
0!
0$
#9375000000
1!
1$
b10010100 '
b10010101 (
#9406250000
0!
0$
#9437500000
1!
1$
b10010101 '
b10010110 (
#9468750000
0!
0$
#9500000000
1!
1$
b10010110 '
b10010111 (
#9531250000
0!
0$
#9562500000
1!
1$
b10010111 '
b10011000 (
#9593750000
0!
0$
#9625000000
1!
1$
b10011000 '
b10011001 (
#9656250000
0!
0$
#9687500000
1!
1$
b10011001 '
b10011010 (
#9718750000
0!
0$
#9750000000
1!
1$
b10011010 '
b10011011 (
#9781250000
0!
0$
#9812500000
1!
1$
b10011011 '
b10011100 (
#9843750000
0!
0$
#9875000000
1!
1$
b10011100 '
b10011101 (
#9906250000
0!
0$
#9937500000
1!
1$
b10011101 '
b10011110 (
#9968750000
0!
0$
#10000000000
1!
1$
b10011110 '
b10011111 (
#10031250000
0!
0$
#10062500000
1!
1$
b10011111 '
b10100000 (
#10093750000
0!
0$
#10125000000
1!
1$
b10100000 '
b10100001 (
#10156250000
0!
0$
#10187500000
1!
1$
b10100001 '
b10100010 (
#10218750000
0!
0$
#10250000000
1!
1$
b10100010 '
b10100011 (
#10281250000
0!
0$
#10312500000
1!
1$
b10100011 '
b10100100 (
#10343750000
0!
0$
#10375000000
1!
1$
b10100100 '
b10100101 (
#10406250000
0!
0$
#10437500000
1!
1$
b10100101 '
b10100110 (
#10468750000
0!
0$
#10500000000
1!
1$
b10100110 '
b10100111 (
#10531250000
0!
0$
#10562500000
1!
1$
b10100111 '
b10101000 (
#10593750000
0!
0$
#10625000000
1!
1$
b10101000 '
b10101001 (
#10656250000
0!
0$
#10687500000
1!
1$
b10101001 '
b10101010 (
#10718750000
0!
0$
#10750000000
1!
1$
b10101010 '
b10101011 (
#10781250000
0!
0$
#10812500000
1!
1$
b10101011 '
b10101100 (
#10843750000
0!
0$
#10875000000
1!
1$
b10101100 '
b10101101 (
#10906250000
0!
0$
#10937500000
1!
1$
b10101101 '
b10101110 (
#10968750000
0!
0$
#11000000000
1!
1$
b10101110 '
b10101111 (
#11031250000
0!
0$
#11062500000
1!
1$
b10101111 '
b10110000 (
#11093750000
0!
0$
#11125000000
1!
1$
b10110000 '
b10110001 (
#11156250000
0!
0$
#11187500000
1!
1$
b10110001 '
b10110010 (
#11218750000
0!
0$
#11250000000
1!
1$
b10110010 '
b10110011 (
#11281250000
0!
0$
#11312500000
1!
1$
b10110011 '
b10110100 (
#11343750000
0!
0$
#11375000000
1!
1$
b10110100 '
b10110101 (
#11406250000
0!
0$
#11437500000
1!
1$
b10110101 '
b10110110 (
#11468750000
0!
0$
#11500000000
1!
1$
b10110110 '
b10110111 (
#11531250000
0!
0$
#11562500000
1!
1$
b10110111 '
b10111000 (
#11593750000
0!
0$
#11625000000
1!
1$
b10111000 '
b10111001 (
#11656250000
0!
0$
#11687500000
1!
1$
b10111001 '
b10111010 (
#11718750000
0!
0$
#11750000000
1!
1$
b10111010 '
b10111011 (
#11781250000
0!
0$
#11812500000
1!
1$
b10111011 '
b10111100 (
#11843750000
0!
0$
#11875000000
1!
1$
b10111100 '
b10111101 (
#11906250000
0!
0$
#11937500000
1!
1$
b10111101 '
b10111110 (
#11968750000
0!
0$
#12000000000
1!
1$
b10111110 '
b10111111 (
#12031250000
0!
0$
#12062500000
1!
1$
b10111111 '
b11000000 (
#12093750000
0!
0$
#12125000000
1!
1$
b11000000 '
b11000001 (
#12156250000
0!
0$
#12187500000
1!
1$
b11000001 '
b11000010 (
#12218750000
0!
0$
#12250000000
1!
1$
b11000010 '
b11000011 (
#12281250000
0!
0$
#12312500000
1!
1$
b11000011 '
b11000100 (
#12343750000
0!
0$
#12375000000
1!
1$
b11000100 '
b11000101 (
#12406250000
0!
0$
#12437500000
1!
1$
b11000101 '
b11000110 (
#12468750000
0!
0$
#12500000000
1!
1$
b11000110 '
b11000111 (
#12531250000
0!
0$
#12562500000
1!
1$
b11000111 '
b11001000 (
#12593750000
0!
0$
#12625000000
1!
1$
b11001000 '
b11001001 (
#12656250000
0!
0$
#12687500000
1!
1$
b11001001 '
b11001010 (
#12718750000
0!
0$
#12750000000
1!
1$
b11001010 '
b11001011 (
#12781250000
0!
0$
#12812500000
1!
1$
b11001011 '
b11001100 (
#12843750000
0!
0$
#12875000000
1!
1$
b11001100 '
b11001101 (
#12906250000
0!
0$
#12937500000
1!
1$
b11001101 '
b11001110 (
#12968750000
0!
0$
#13000000000
1!
1$
b11001110 '
b11001111 (
#13031250000
0!
0$
#13062500000
1!
1$
b11001111 '
b11010000 (
#13093750000
0!
0$
#13125000000
1!
1$
b11010000 '
b11010001 (
#13156250000
0!
0$
#13187500000
1!
1$
b11010001 '
b11010010 (
#13218750000
0!
0$
#13250000000
1!
1$
b11010010 '
b11010011 (
#13281250000
0!
0$
#13312500000
1!
1$
b11010011 '
b11010100 (
#13343750000
0!
0$
#13375000000
1!
1$
b11010100 '
b11010101 (
#13406250000
0!
0$
#13437500000
1!
1$
b11010101 '
b11010110 (
#13468750000
0!
0$
#13500000000
1!
1$
b11010110 '
b11010111 (
#13531250000
0!
0$
#13562500000
1!
1$
b11010111 '
b11011000 (
#13593750000
0!
0$
#13625000000
1!
1$
b11011000 '
b11011001 (
#13656250000
0!
0$
#13687500000
1!
1$
b11011001 '
b11011010 (
#13718750000
0!
0$
#13750000000
1!
1$
b11011010 '
b11011011 (
#13781250000
0!
0$
#13812500000
1!
1$
b11011011 '
b11011100 (
#13843750000
0!
0$
#13875000000
1!
1$
b11011100 '
b11011101 (
#13906250000
0!
0$
#13937500000
1!
1$
b11011101 '
b11011110 (
#13968750000
0!
0$
#14000000000
1!
1$
b11011110 '
b11011111 (
#14031250000
0!
0$
#14062500000
1!
1$
b11011111 '
b11100000 (
#14093750000
0!
0$
#14125000000
1!
1$
b11100000 '
b11100001 (
#14156250000
0!
0$
#14187500000
1!
1$
b11100001 '
b11100010 (
#14218750000
0!
0$
#14250000000
1!
1$
b11100010 '
b11100011 (
#14281250000
0!
0$
#14312500000
1!
1$
b11100011 '
b11100100 (
#14343750000
0!
0$
#14375000000
1!
1$
b11100100 '
b11100101 (
#14406250000
0!
0$
#14437500000
1!
1$
b11100101 '
b11100110 (
#14468750000
0!
0$
#14500000000
1!
1$
b11100110 '
b11100111 (
#14531250000
0!
0$
#14562500000
1!
1$
b11100111 '
b11101000 (
#14593750000
0!
0$
#14625000000
1!
1$
b11101000 '
b11101001 (
#14656250000
0!
0$
#14687500000
1!
1$
b11101001 '
b11101010 (
#14718750000
0!
0$
#14750000000
1!
1$
b11101010 '
b11101011 (
#14781250000
0!
0$
#14812500000
1!
1$
b11101011 '
b11101100 (
#14843750000
0!
0$
#14875000000
1!
1$
b11101100 '
b11101101 (
#14906250000
0!
0$
#14937500000
1!
1$
b11101101 '
b11101110 (
#14968750000
0!
0$
#15000000000
1!
1$
b11101110 '
b11101111 (
#15031250000
0!
0$
#15062500000
1!
1$
b11101111 '
b11110000 (
#15093750000
0!
0$
#15125000000
1!
1$
b11110000 '
b11110001 (
#15156250000
0!
0$
#15187500000
1!
1$
b11110001 '
b11110010 (
#15218750000
0!
0$
#15250000000
1!
1$
b11110010 '
b11110011 (
#15281250000
0!
0$
#15312500000
1!
1$
b11110011 '
b11110100 (
#15343750000
0!
0$
#15375000000
1!
1$
b11110100 '
b11110101 (
#15406250000
0!
0$
#15437500000
1!
1$
b11110101 '
b11110110 (
#15468750000
0!
0$
#15500000000
1!
1$
b11110110 '
b11110111 (
#15531250000
0!
0$
#15562500000
1!
1$
b11110111 '
b11111000 (
#15593750000
0!
0$
#15625000000
1!
1$
b11111000 '
b11111001 (
#15656250000
0!
0$
#15687500000
1!
1$
b11111001 '
b11111010 (
#15718750000
0!
0$
#15750000000
1!
1$
b11111010 '
b11111011 (
#15781250000
0!
0$
#15812500000
1!
1$
b11111011 '
b11111100 (
#15843750000
0!
0$
#15875000000
1!
1$
b11111100 '
b11111101 (
#15906250000
0!
0$
#15937500000
1!
1$
b11111101 '
b11111110 (
#15968750000
0!
0$
#16000000000
1!
1$
b11111110 '
b11111111 (
#16031250000
0!
0$
#16062500000
1!
1$
b11111111 '
b100000000 (
#16093750000
0!
0$
#16125000000
1!
1$
b100000000 '
b100000001 (
#16156250000
0!
0$
#16187500000
1!
1$
b100000001 '
b100000010 (
#16218750000
0!
0$
#16250000000
1!
1$
b100000010 '
b100000011 (
#16281250000
0!
0$
#16312500000
1!
1$
b100000011 '
b100000100 (
#16343750000
0!
0$
#16375000000
1!
1$
b100000100 '
b100000101 (
#16406250000
0!
0$
#16437500000
1!
1$
b100000101 '
b100000110 (
#16468750000
0!
0$
#16500000000
1!
1$
b100000110 '
b100000111 (
#16531250000
0!
0$
#16562500000
1!
1$
b100000111 '
b100001000 (
#16593750000
0!
0$
#16625000000
1!
1$
b100001000 '
b100001001 (
#16656250000
0!
0$
#16687500000
1!
1$
b100001001 '
b100001010 (
#16718750000
0!
0$
#16750000000
1!
1$
b100001010 '
b100001011 (
#16781250000
0!
0$
#16812500000
1!
1$
b100001011 '
b100001100 (
#16843750000
0!
0$
#16875000000
1!
1$
b100001100 '
b100001101 (
#16906250000
0!
0$
#16937500000
1!
1$
b100001101 '
b100001110 (
#16968750000
0!
0$
#17000000000
1!
1$
b100001110 '
b100001111 (
#17031250000
0!
0$
#17062500000
1!
1$
b100001111 '
b100010000 (
#17093750000
0!
0$
#17125000000
1!
1$
b100010000 '
b100010001 (
#17156250000
0!
0$
#17187500000
1!
1$
b100010001 '
b100010010 (
#17218750000
0!
0$
#17250000000
1!
1$
b100010010 '
b100010011 (
#17281250000
0!
0$
#17312500000
1!
1$
b100010011 '
b100010100 (
#17343750000
0!
0$
#17375000000
1!
1$
b100010100 '
b100010101 (
#17406250000
0!
0$
#17437500000
1!
1$
b100010101 '
b100010110 (
#17468750000
0!
0$
#17500000000
1!
1$
b100010110 '
b100010111 (
#17531250000
0!
0$
#17562500000
1!
1$
b100010111 '
b100011000 (
#17593750000
0!
0$
#17625000000
1!
1$
b100011000 '
b100011001 (
#17656250000
0!
0$
#17687500000
1!
1$
b100011001 '
b100011010 (
#17718750000
0!
0$
#17750000000
1!
1$
b100011010 '
b100011011 (
#17781250000
0!
0$
#17812500000
1!
1$
b100011011 '
b100011100 (
#17843750000
0!
0$
#17875000000
1!
1$
b100011100 '
b100011101 (
#17906250000
0!
0$
#17937500000
1!
1$
b100011101 '
b100011110 (
#17968750000
0!
0$
#18000000000
1!
1$
b100011110 '
b100011111 (
#18031250000
0!
0$
#18062500000
1!
1$
b100011111 '
b100100000 (
#18093750000
0!
0$
#18125000000
1!
1$
b100100000 '
b100100001 (
#18156250000
0!
0$
#18187500000
1!
1$
b100100001 '
b100100010 (
#18218750000
0!
0$
#18250000000
1!
1$
b100100010 '
b100100011 (
#18281250000
0!
0$
#18312500000
1!
1$
b100100011 '
b100100100 (
#18343750000
0!
0$
#18375000000
1!
1$
b100100100 '
b100100101 (
#18406250000
0!
0$
#18437500000
1!
1$
b100100101 '
b100100110 (
#18468750000
0!
0$
#18500000000
1!
1$
b100100110 '
b100100111 (
#18531250000
0!
0$
#18562500000
1!
1$
b100100111 '
b100101000 (
#18593750000
0!
0$
#18625000000
1!
1$
b100101000 '
b100101001 (
#18656250000
0!
0$
#18687500000
1!
1$
b100101001 '
b100101010 (
#18718750000
0!
0$
#18750000000
1!
1$
b100101010 '
b100101011 (
#18781250000
0!
0$
#18812500000
1!
1$
b100101011 '
b100101100 (
#18843750000
0!
0$
#18875000000
1!
1$
b100101100 '
b100101101 (
#18906250000
0!
0$
#18937500000
1!
1$
b100101101 '
b100101110 (
#18968750000
0!
0$
#19000000000
1!
1$
b100101110 '
b100101111 (
#19031250000
0!
0$
#19062500000
1!
1$
b100101111 '
b100110000 (
#19093750000
0!
0$
#19125000000
1!
1$
b100110000 '
b100110001 (
#19156250000
0!
0$
#19187500000
1!
1$
b100110001 '
b100110010 (
#19218750000
0!
0$
#19250000000
1!
1$
b100110010 '
b100110011 (
#19281250000
0!
0$
#19312500000
1!
1$
b100110011 '
b100110100 (
#19343750000
0!
0$
#19375000000
1!
1$
b100110100 '
b100110101 (
#19406250000
0!
0$
#19437500000
1!
1$
b100110101 '
b100110110 (
#19468750000
0!
0$
#19500000000
1!
1$
b100110110 '
b100110111 (
#19531250000
0!
0$
#19562500000
1!
1$
b100110111 '
b100111000 (
#19593750000
0!
0$
#19625000000
1!
1$
b100111000 '
b100111001 (
#19656250000
0!
0$
#19687500000
1!
1$
b100111001 '
b100111010 (
#19718750000
0!
0$
#19750000000
1!
1$
b100111010 '
b100111011 (
#19781250000
0!
0$
#19812500000
1!
1$
b100111011 '
b100111100 (
#19843750000
0!
0$
#19875000000
1!
1$
b100111100 '
b100111101 (
#19906250000
0!
0$
#19937500000
1!
1$
b100111101 '
b100111110 (
#19968750000
0!
0$
#20000000000
1!
1$
b100111110 '
b100111111 (
#20031250000
0!
0$
#20062500000
1!
1$
b100111111 '
b101000000 (
#20093750000
0!
0$
#20125000000
1!
1$
b101000000 '
b101000001 (
#20156250000
0!
0$
#20187500000
1!
1$
b101000001 '
b101000010 (
#20218750000
0!
0$
#20250000000
1!
1$
b101000010 '
b101000011 (
#20281250000
0!
0$
#20312500000
1!
1$
b101000011 '
b101000100 (
#20343750000
0!
0$
#20375000000
1!
1$
b101000100 '
b101000101 (
#20406250000
0!
0$
#20437500000
1!
1$
b101000101 '
b101000110 (
#20468750000
0!
0$
#20500000000
1!
1$
b101000110 '
b101000111 (
#20531250000
0!
0$
#20562500000
1!
1$
b101000111 '
b101001000 (
#20593750000
0!
0$
#20625000000
1!
1$
b101001000 '
b101001001 (
#20656250000
0!
0$
#20687500000
1!
1$
b101001001 '
b101001010 (
#20718750000
0!
0$
#20750000000
1!
1$
b101001010 '
b101001011 (
#20781250000
0!
0$
#20812500000
1!
1$
b101001011 '
b101001100 (
#20843750000
0!
0$
#20875000000
1!
1$
b101001100 '
b101001101 (
#20906250000
0!
0$
#20937500000
1!
1$
b101001101 '
b101001110 (
#20968750000
0!
0$
#21000000000
1!
1$
b101001110 '
b101001111 (
#21031250000
0!
0$
#21062500000
1!
1$
b101001111 '
b101010000 (
#21093750000
0!
0$
#21125000000
1!
1$
b101010000 '
b101010001 (
#21156250000
0!
0$
#21187500000
1!
1$
b101010001 '
b101010010 (
#21218750000
0!
0$
#21250000000
1!
1$
b101010010 '
b101010011 (
#21281250000
0!
0$
#21312500000
1!
1$
b101010011 '
b101010100 (
#21343750000
0!
0$
#21375000000
1!
1$
b101010100 '
b101010101 (
#21406250000
0!
0$
#21437500000
1!
1$
b101010101 '
b101010110 (
#21468750000
0!
0$
#21500000000
1!
1$
b101010110 '
b101010111 (
#21531250000
0!
0$
#21562500000
1!
1$
b101010111 '
b101011000 (
#21593750000
0!
0$
#21625000000
1!
1$
b101011000 '
b101011001 (
#21656250000
0!
0$
#21687500000
1!
1$
b101011001 '
b101011010 (
#21718750000
0!
0$
#21750000000
1!
1$
b101011010 '
b101011011 (
#21781250000
0!
0$
#21812500000
1!
1$
b101011011 '
b101011100 (
#21843750000
0!
0$
#21875000000
1!
1$
b101011100 '
b101011101 (
#21906250000
0!
0$
#21937500000
1!
1$
b101011101 '
b101011110 (
#21968750000
0!
0$
#22000000000
1!
1$
b101011110 '
b101011111 (
#22031250000
0!
0$
#22062500000
1!
1$
b101011111 '
b101100000 (
#22093750000
0!
0$
#22125000000
1!
1$
b101100000 '
b101100001 (
#22156250000
0!
0$
#22187500000
1!
1$
b101100001 '
b101100010 (
#22218750000
0!
0$
#22250000000
1!
1$
b101100010 '
b101100011 (
#22281250000
0!
0$
#22312500000
1!
1$
b101100011 '
b101100100 (
#22343750000
0!
0$
#22375000000
1!
1$
b101100100 '
b101100101 (
#22406250000
0!
0$
#22437500000
1!
1$
b101100101 '
b101100110 (
#22468750000
0!
0$
#22500000000
1!
1$
b101100110 '
b101100111 (
#22531250000
0!
0$
#22562500000
1!
1$
b101100111 '
b101101000 (
#22593750000
0!
0$
#22625000000
1!
1$
b101101000 '
b101101001 (
#22656250000
0!
0$
#22687500000
1!
1$
b101101001 '
b101101010 (
#22718750000
0!
0$
#22750000000
1!
1$
b101101010 '
b101101011 (
#22781250000
0!
0$
