VHDL/quadrature_decoder/direction_computer.vhd
library ieee;
use ieee.std_logic_1164.all;

entity direction_computer is
	port(
		A : in std_logic; -- Channel A of the incremental encoder.
		B : in std_logic; -- Channel B of the incremental encoder.
		prev_state : in std_logic_vector(1 downto 0); -- The state of channel A and B respectively just before a change in state of channel A.
		dir : out std_logic -- When the bit is asserted, the direction is CW, otherwise it is CCW.
	);
end direction_computer;

architecture behav_arch of direction_computer is
begin
	process(A,B,prev_state)
		variable test : std_logic_vector(3 downto 0);
		variable current_state : std_logic_vector(1 downto 0);
	begin
		-- On the rising OR falling edge of the A signal, the direction can be computed.
		-- The conditions to compute the direction are different for the rising and falling edge of A.
		-- The conditions to determine CW and CCW rotation are:
		--		Rising edge of A:
		--			CW:
		-- 				previous state -> A = '0', B = '1'
		-- 				current state  -> A = '1', B = '1'
		--			CCW:
		-- 				previous state -> A = '0', B = '0'
		-- 				current state  -> A = '1', B = '0'
		-- 		Falling adge of A:
		--			CW:
		-- 				previous state -> A = '1', B = '0'
		-- 				current state  -> A = '0', B = '0'
		--			CCW:
		-- 				previous state -> A = '1', B = '1'
		-- 				current state  -> A = '0', B = '1'
		--
		if(A'event) then
			current_state := A & B;
			test := prev_state & current_state;
			-- Rising edge of A
			if(A = '1' and A'last_value = '0') then
				if(test = "0111") then
					dir <= '1'; -- CW
				else
					dir <= '0'; -- CCW
				end if;
			-- Falling edge of A
			elsif(A = '0' and A'last_value = '1') then
				if(test = "1000") then
					dir <= '1'; -- CW
				else
					dir <= '0'; -- CCW
				end if;
			end if;
		end if;
	end process;
end behav_arch;

VHDL/quadrature_decoder/previous_state_register.vhd
library ieee;
use ieee.std_logic_1164.all;

entity previous_state_register is
	port(
		A 			: in std_logic;
		B 			: in std_logic;
		prev_state 	: out std_logic_vector(1 downto 0)
	);
end previous_state_register;

architecture behav_arch of previous_state_register is
begin
	process(A,B)
	begin
		if(B'event) then
			prev_state <= A & B;
		end if;
	end process;
end behav_arch;

VHDL/quadrature_decoder/testbenches/direction_computer_tb.vhd
library ieee;
use ieee.std_logic_1164.all;

entity direction_computer_tb is
end direction_computer_tb;

architecture tb_arch of direction_computer_tb is

component direction_computer is
	port(
		A : in std_logic; -- Channel A of the incremental encoder.
		B : in std_logic; -- Channel B of the incremental encoder.
		prev_state : in std_logic_vector(1 downto 0); -- The state of channel A and B respectively just before a change in state of channel A.
		dir : out std_logic -- When the bit is asserted, the direction is CW, otherwise it is CCW.
	);
end component;

component previous_state_register is
	port(
		A 			: in std_logic;
		B 			: in std_logic;
		prev_state 	: out std_logic_vector(1 downto 0)
	);
end component;

for test_unit : direction_computer use entity WORK.direction_computer(behav_arch);
for prev_state_comp : previous_state_register use entity WORK.previous_state_register(behav_arch); 

signal in_A, in_B : std_logic := '1';
signal p_state : std_logic_vector(1 downto 0);
signal direction : std_logic;

signal clkgen : std_logic := '1';

begin

	prev_state_comp : previous_state_register port map(
		A => in_A,
		B => in_B,
		prev_state => p_state
	);

	test_unit : direction_computer port map(
		A => in_A,
		B => in_B,
		prev_state => p_state,
		dir => direction
	);

	-- Let T = 20ns for a continuous constant speed rotation.
	process
		variable T : integer := 20;
	begin
		in_A <= '1'; wait for 10 ns;
		in_A <= '0'; wait for 20 ns; wait for 10 ns;
		in_A <= '1'; wait for 10 ns;
		in_A <= '0'; wait for 10 ns;
		in_A <= '1'; wait for 20 ns;
		in_A <= '0'; wait for 10 ns;
		in_A <= '1'; wait for 10 ns;
		in_A <= '0'; wait for 20 ns;
		in_A <= '1'; wait for 10 ns;
		in_A <= 'X';
	end process;

	-- Clk used to produced signal B as a 90 deg shifted version of signal A
	clkgen <= not clkgen after 5 ns;
	-- Signal B
	process(clkgen,in_B)
	begin
		if(clkgen'event and clkgen = '0') then
			in_B <= not in_B;
		end if;
	end process;

end tb_arch;

VHDL/quadrature_decoder/testbenches/tb_wave_forms_files/direction_computer_tb.vcd
$date
  Fri Jul  3 12:25:08 2020
$end
$version
  GHDL v0
$end
$timescale
  1 fs
$end
$scope module standard $end
$upscope $end
$scope module std_logic_1164 $end
$upscope $end
$scope module direction_computer_tb $end
$var reg 1 ! in_a $end
$var reg 1 " in_b $end
$var reg 2 # p_state[1:0] $end
$var reg 1 $ direction $end
$var reg 1 % clkgen $end
$scope module prev_state_comp $end
$var reg 1 & a $end
$var reg 1 ' b $end
$var reg 2 ( prev_state[1:0] $end
$upscope $end
$scope module test_unit $end
$var reg 1 ) a $end
$var reg 1 * b $end
$var reg 2 + prev_state[1:0] $end
$var reg 1 , dir $end
$upscope $end
$upscope $end
$enddefinitions $end
#0
1!
1"
bUU #
U$
1%
1&
1'
bUU (
1)
1*
bUU +
U,
#5000000
0"
b10 #
0%
0'
b10 (
0*
b10 +
#10000000
0!
1$
1%
0&
0)
1,
#15000000
1"
b01 #
0%
1'
b01 (
1*
b01 +
#20000000
1%
#25000000
0"
b00 #
0%
0'
b00 (
0*
b00 +
#30000000
1%
#35000000
1"
b01 #
0%
1'
b01 (
1*
b01 +
#40000000
1!
1%
1&
1)
#45000000
0"
b10 #
0%
0'
b10 (
0*
b10 +
#50000000
0!
1%
0&
0)
#55000000
1"
b01 #
0%
1'
b01 (
1*
b01 +
#60000000
1!
1%
1&
1)
#65000000
0"
b10 #
0%
0'
b10 (
0*
b10 +
#70000000
1%
#75000000
1"
b11 #
0%
1'
b11 (
1*
b11 +
#80000000
0!
0$
1%
0&
0)
0,
#85000000
0"
b00 #
0%
0'
b00 (
0*
b00 +
#90000000
1!
1%
1&
1)
#95000000
1"
b11 #
0%
1'
b11 (
1*
b11 +
#100000000
0!
1%
0&
0)
#105000000
0"
b00 #
0%
0'
b00 (
0*
b00 +
#110000000
1%
#115000000
1"
b01 #
0%
1'
b01 (
1*
b01 +
#120000000
1!
1$
1%
1&
1)
1,
#125000000
0"
b10 #
0%
0'
b10 (
0*
b10 +
#130000000
1%
#135000000
1"
b11 #
0%
1'
b11 (
1*
b11 +
#140000000
0!
0$
1%
0&
0)
0,
