VHDL/quadrature_decoder/position_computer.vhd
library ieee;
use ieee.std_logic_1164.all;
use ieee.numeric_std.all;

entity position_computer is
	port(
		A 				: in std_logic;
		B 				: in std_logic;
		reset			: in std_logic;
		direction		: out std_logic;
		position		: out std_logic_vector(12 downto 0)
	);
end position_computer;

architecture behav_arch of position_computer is

type state_type is (S0,S1,S2,S3); -- machine states
signal state : state_type;
signal dir : std_logic;
signal count : signed(12 downto 0);

begin
	process(A,B) -- State Machine Process
		variable wave : std_logic_vector(1 downto 0);
	begin
		if (reset = '1') then
			state <= S0;
			dir <= '1';
			count <= (others => '0');
		elsif (A'event or B'event) then
			wave := A&B;

			case state is
				when S0 =>
					if (wave = "01") then
						State <= S1;
						dir <= '1';
					elsif (wave = "10") then
						State <= S2;
						dir <= '0';
						count <= count - 1;
					end if;

				when S1 =>
					if (wave = "11") then
						State <= S3;
						dir <= '1';
					elsif (wave = "00") then
						State <= S0;
						dir <= '0';
					end if;

				when S2 =>
					if (wave = "00") then
						State <= S0;
						dir <= '1';
						count <= count + 1;
					elsif (wave = "11") then
						State <= S3;
						dir <= '0';
					end if;

				when S3 =>
					if (wave = "10") then
						State <= S2;
						dir <= '1';
					elsif (wave = "01") then
						State <= S1;
						dir <= '0';
					end if;
			end case;
		end if;
	end process;

	-- Output logic
	position <= std_logic_vector(count);
	direction <= dir;

end behav_arch;

VHDL/quadrature_decoder/testbenches/dir_pos_computer.vhd
library ieee;
use ieee.std_logic_1164.all;

entity position_computer_tb is
end position_computer_tb;

architecture tb_arch of position_computer_tb is

component position_computer is
	port(
		A 				: in std_logic;
		B 				: in std_logic;
		reset			: in std_logic;
		direction		: out std_logic;
		position		: out std_logic_vector(12 downto 0)
	);
end component;

for test_unit : position_computer use entity WORK.position_computer(behav_arch);

signal in_A, in_B : std_logic := '1';
signal Z : std_logic := '0';
signal direction : std_logic;
signal position : std_logic_vector(12 downto 0);

signal clk : std_logic := '0';
signal clkgen : std_logic := '1';

begin

	test_unit : position_computer port map(
		A => in_A,
		B => in_B,
		reset => Z,
		direction => direction,
		position => position
	);

	-- Time of rotations are in micro-seconds.

	process
	begin
		wait for 5000 ns;
		Z <= '1';
		wait for 5000 ns;
		Z <= '0';
		wait;
	end process;

	clk <= not clk after 62.5 ns; -- 16 MHz clock

	-- Let T = 20us for a continuous constant speed rotation.
	process
	begin
		in_A <= '0'; wait for 10000 ns;
		in_A <= '1'; wait for 10000 ns; -- -1 	cycle
		in_A <= '0'; wait for 10000 ns;
		in_A <= '1'; wait for 10000 ns; -- -1 	cycle
		in_A <= '0'; wait for 10000 ns;
		in_A <= '1'; wait for 10000 ns; -- -1 	cycle
		in_A <= '0'; wait for 10000 ns;
		in_A <= '1'; wait for 10000 ns; -- -1 	cycle
		in_A <= '0'; wait for 10000 ns;
		in_A <= '1'; wait for 10000 ns; -- -1 	cycle
		-- Direction change
		in_A <= '1'; wait for 10000 ns;
		in_A <= '0'; wait for 10000 ns; -- +1 	cycle
		in_A <= '1'; wait for 10000 ns;
		in_A <= '0'; wait for 10000 ns; -- +1 	cycle
		in_A <= '1'; wait for 10000 ns;
		in_A <= '0'; wait for 10000 ns; -- +1 	cycle
		in_A <= '1'; wait for 10000 ns;
		in_A <= '0'; wait for 10000 ns; -- +1 	cycle
		in_A <= 'U';
		
	end process;

	-- Clk used to produced signal B as a 90 deg shifted version of signal A
	clkgen <= not clkgen after 5000 ns;
	-- Signal B
	process(clkgen,in_B)
	begin
		if(clkgen'event and clkgen = '0') then
			in_B <= not in_B;
		end if;
	end process;

end tb_arch;

VHDL/quadrature_decoder/testbenches/tb_wave_forms_files/position_computer_tb.vcd
$date
  Sat Jul  4 10:01:34 2020
$end
$version
  GHDL v0
$end
$timescale
  1 fs
$end
$scope module standard $end
$upscope $end
$scope module std_logic_1164 $end
$upscope $end
$scope module numeric_std $end
$upscope $end
$scope module position_computer_tb $end
$var reg 1 ! in_a $end
$var reg 1 " in_b $end
$var reg 1 # z $end
$var reg 1 $ direction $end
$var reg 13 % position[12:0] $end
$var reg 1 & clk $end
$var reg 1 ' clkgen $end
$scope module test_unit $end
$var reg 1 ( a $end
$var reg 1 ) b $end
$var reg 1 * reset $end
$var reg 1 + direction $end
$var reg 13 , position[12:0] $end
$comment state is not handled $end
$var reg 1 - dir $end
$var reg 13 . count[12:0] $end
$upscope $end
$upscope $end
$enddefinitions $end
#0
0!
1"
0#
1$
bUUUUUUUUUUUUU %
0&
1'
0(
1)
0*
1+
bUUUUUUUUUUUUU ,
1-
bUUUUUUUUUUUUU .
#62500000
1&
#125000000
0&
#187500000
1&
#250000000
0&
#312500000
1&
#375000000
0&
#437500000
1&
#500000000
0&
#562500000
1&
#625000000
0&
#687500000
1&
#750000000
0&
#812500000
1&
#875000000
0&
#937500000
1&
#1000000000
0&
#1062500000
1&
#1125000000
0&
#1187500000
1&
#1250000000
0&
#1312500000
1&
#1375000000
0&
#1437500000
1&
#1500000000
0&
#1562500000
1&
#1625000000
0&
#1687500000
1&
#1750000000
0&
#1812500000
1&
#1875000000
0&
#1937500000
1&
#2000000000
0&
#2062500000
1&
#2125000000
0&
#2187500000
1&
#2250000000
0&
#2312500000
1&
#2375000000
0&
#2437500000
1&
#2500000000
0&
#2562500000
1&
#2625000000
0&
#2687500000
1&
#2750000000
0&
#2812500000
1&
#2875000000
0&
#2937500000
1&
#3000000000
0&
#3062500000
1&
#3125000000
0&
#3187500000
1&
#3250000000
0&
#3312500000
1&
#3375000000
0&
#3437500000
1&
#3500000000
0&
#3562500000
1&
#3625000000
0&
#3687500000
1&
#3750000000
0&
#3812500000
1&
#3875000000
0&
#3937500000
1&
#4000000000
0&
#4062500000
1&
#4125000000
0&
#4187500000
1&
#4250000000
0&
#4312500000
1&
#4375000000
0&
#4437500000
1&
#4500000000
0&
#4562500000
1&
#4625000000
0&
#4687500000
1&
#4750000000
0&
#4812500000
1&
#4875000000
0&
#4937500000
1&
#5000000000
0"
1#
b0000000000000 %
0&
0'
0)
1*
b0000000000000 ,
b0000000000000 .
#5062500000
1&
#5125000000
0&
#5187500000
1&
#5250000000
0&
#5312500000
1&
#5375000000
0&
#5437500000
1&
#5500000000
0&
#5562500000
1&
#5625000000
0&
#5687500000
1&
#5750000000
0&
#5812500000
1&
#5875000000
0&
#5937500000
1&
#6000000000
0&
#6062500000
1&
#6125000000
0&
#6187500000
1&
#6250000000
0&
#6312500000
1&
#6375000000
0&
#6437500000
1&
#6500000000
0&
#6562500000
1&
#6625000000
0&
#6687500000
1&
#6750000000
0&
#6812500000
1&
#6875000000
0&
#6937500000
1&
#7000000000
0&
#7062500000
1&
#7125000000
0&
#7187500000
1&
#7250000000
0&
#7312500000
1&
#7375000000
0&
#7437500000
1&
#7500000000
0&
#7562500000
1&
#7625000000
0&
#7687500000
1&
#7750000000
0&
#7812500000
1&
#7875000000
0&
#7937500000
1&
#8000000000
0&
#8062500000
1&
#8125000000
0&
#8187500000
1&
#8250000000
0&
#8312500000
1&
#8375000000
0&
#8437500000
1&
#8500000000
0&
#8562500000
1&
#8625000000
0&
#8687500000
1&
#8750000000
0&
#8812500000
1&
#8875000000
0&
#8937500000
1&
#9000000000
0&
#9062500000
1&
#9125000000
0&
#9187500000
1&
#9250000000
0&
#9312500000
1&
#9375000000
0&
#9437500000
1&
#9500000000
0&
#9562500000
1&
#9625000000
0&
#9687500000
1&
#9750000000
0&
#9812500000
1&
#9875000000
0&
#9937500000
1&
#10000000000
1!
0#
0$
b1111111111111 %
0&
1'
1(
0*
0+
b1111111111111 ,
0-
b1111111111111 .
#10062500000
1&
#10125000000
0&
#10187500000
1&
#10250000000
0&
#10312500000
1&
#10375000000
0&
#10437500000
1&
#10500000000
0&
#10562500000
1&
#10625000000
0&
#10687500000
1&
#10750000000
0&
#10812500000
1&
#10875000000
0&
#10937500000
1&
#11000000000
0&
#11062500000
1&
#11125000000
0&
#11187500000
1&
#11250000000
0&
#11312500000
1&
#11375000000
0&
#11437500000
1&
#11500000000
0&
#11562500000
1&
#11625000000
0&
#11687500000
1&
#11750000000
0&
#11812500000
1&
#11875000000
0&
#11937500000
1&
#12000000000
0&
#12062500000
1&
#12125000000
0&
#12187500000
1&
#12250000000
0&
#12312500000
1&
#12375000000
0&
#12437500000
1&
#12500000000
0&
#12562500000
1&
#12625000000
0&
#12687500000
1&
#12750000000
0&
#12812500000
1&
#12875000000
0&
#12937500000
1&
#13000000000
0&
#13062500000
1&
#13125000000
0&
#13187500000
1&
#13250000000
0&
#13312500000
1&
#13375000000
0&
#13437500000
1&
#13500000000
0&
#13562500000
1&
#13625000000
0&
#13687500000
1&
#13750000000
0&
#13812500000
1&
#13875000000
0&
#13937500000
1&
#14000000000
0&
#14062500000
1&
#14125000000
0&
#14187500000
1&
#14250000000
0&
#14312500000
1&
#14375000000
0&
#14437500000
1&
#14500000000
0&
#14562500000
1&
#14625000000
0&
#14687500000
1&
#14750000000
0&
#14812500000
1&
#14875000000
0&
#14937500000
1&
#15000000000
1"
0&
0'
1)
#15062500000
1&
#15125000000
0&
#15187500000
1&
#15250000000
0&
#15312500000
1&
#15375000000
0&
#15437500000
1&
#15500000000
0&
#15562500000
1&
#15625000000
0&
#15687500000
1&
#15750000000
0&
#15812500000
1&
#15875000000
0&
#15937500000
1&
#16000000000
0&
#16062500000
1&
#16125000000
0&
#16187500000
1&
#16250000000
0&
#16312500000
1&
#16375000000
0&
#16437500000
1&
#16500000000
0&
#16562500000
1&
#16625000000
0&
#16687500000
1&
#16750000000
0&
#16812500000
1&
#16875000000
0&
#16937500000
1&
#17000000000
0&
#17062500000
1&
#17125000000
0&
#17187500000
1&
#17250000000
0&
#17312500000
1&
#17375000000
0&
#17437500000
1&
#17500000000
0&
#17562500000
1&
#17625000000
0&
#17687500000
1&
#17750000000
0&
#17812500000
1&
#17875000000
0&
#17937500000
1&
#18000000000
0&
#18062500000
1&
#18125000000
0&
#18187500000
1&
#18250000000
0&
#18312500000
1&
#18375000000
0&
#18437500000
1&
#18500000000
0&
#18562500000
1&
#18625000000
0&
#18687500000
1&
#18750000000
0&
#18812500000
1&
#18875000000
0&
#18937500000
1&
#19000000000
0&
#19062500000
1&
#19125000000
0&
#19187500000
1&
#19250000000
0&
#19312500000
1&
#19375000000
0&
#19437500000
1&
#19500000000
0&
#19562500000
1&
#19625000000
0&
#19687500000
1&
#19750000000
0&
#19812500000
1&
#19875000000
0&
#19937500000
1&
#20000000000
0!
0&
1'
0(
#20062500000
1&
#20125000000
0&
#20187500000
1&
#20250000000
0&
#20312500000
1&
#20375000000
0&
#20437500000
1&
#20500000000
0&
#20562500000
1&
#20625000000
0&
#20687500000
1&
#20750000000
0&
#20812500000
1&
#20875000000
0&
#20937500000
1&
#21000000000
0&
#21062500000
1&
#21125000000
0&
#21187500000
1&
#21250000000
0&
#21312500000
1&
#21375000000
0&
#21437500000
1&
#21500000000
0&
#21562500000
1&
#21625000000
0&
#21687500000
1&
#21750000000
0&
#21812500000
1&
#21875000000
0&
#21937500000
1&
#22000000000
0&
#22062500000
1&
#22125000000
0&
#22187500000
1&
#22250000000
0&
#22312500000
1&
#22375000000
0&
#22437500000
1&
#22500000000
0&
#22562500000
1&
#22625000000
0&
#22687500000
1&
#22750000000
0&
#22812500000
1&
#22875000000
0&
#22937500000
1&
#23000000000
0&
#23062500000
1&
#23125000000
0&
#23187500000
1&
#23250000000
0&
#23312500000
1&
#23375000000
0&
#23437500000
1&
#23500000000
0&
#23562500000
1&
#23625000000
0&
#23687500000
1&
#23750000000
0&
#23812500000
1&
#23875000000
0&
#23937500000
1&
#24000000000
0&
#24062500000
1&
#24125000000
0&
#24187500000
1&
#24250000000
0&
#24312500000
1&
#24375000000
0&
#24437500000
1&
#24500000000
0&
#24562500000
1&
#24625000000
0&
#24687500000
1&
#24750000000
0&
#24812500000
1&
#24875000000
0&
#24937500000
1&
#25000000000
0"
0&
0'
0)
#25062500000
1&
#25125000000
0&
#25187500000
1&
#25250000000
0&
#25312500000
1&
#25375000000
0&
#25437500000
1&
#25500000000
0&
#25562500000
1&
#25625000000
0&
#25687500000
1&
#25750000000
0&
#25812500000
1&
#25875000000
0&
#25937500000
1&
#26000000000
0&
#26062500000
1&
#26125000000
0&
#26187500000
1&
#26250000000
0&
#26312500000
1&
#26375000000
0&
#26437500000
1&
#26500000000
0&
#26562500000
1&
#26625000000
0&
#26687500000
1&
#26750000000
0&
#26812500000
1&
#26875000000
0&
#26937500000
1&
#27000000000
0&
#27062500000
1&
#27125000000
0&
#27187500000
1&
#27250000000
0&
#27312500000
1&
#27375000000
0&
#27437500000
1&
#27500000000
0&
#27562500000
1&
#27625000000
0&
#27687500000
1&
#27750000000
0&
#27812500000
1&
#27875000000
0&
#27937500000
1&
#28000000000
0&
#28062500000
1&
#28125000000
0&
#28187500000
1&
#28250000000
0&
#28312500000
1&
#28375000000
0&
#28437500000
1&
#28500000000
0&
#28562500000
1&
#28625000000
0&
#28687500000
1&
#28750000000
0&
#28812500000
1&
#28875000000
0&
#28937500000
1&
#29000000000
0&
#29062500000
1&
#29125000000
0&
#29187500000
1&
#29250000000
0&
#29312500000
1&
#29375000000
0&
#29437500000
1&
#29500000000
0&
#29562500000
1&
#29625000000
0&
#29687500000
1&
#29750000000
0&
#29812500000
1&
#29875000000
0&
#29937500000
1&
#30000000000
1!
b1111111111110 %
0&
1'
1(
b1111111111110 ,
b1111111111110 .
#30062500000
1&
#30125000000
0&
#30187500000
1&
#30250000000
0&
#30312500000
1&
#30375000000
0&
#30437500000
1&
#30500000000
0&
#30562500000
1&
#30625000000
0&
#30687500000
1&
#30750000000
0&
#30812500000
1&
#30875000000
0&
#30937500000
1&
#31000000000
0&
#31062500000
1&
#31125000000
0&
#31187500000
1&
#31250000000
0&
#31312500000
1&
#31375000000
0&
#31437500000
1&
#31500000000
0&
#31562500000
1&
#31625000000
0&
#31687500000
1&
#31750000000
0&
#31812500000
1&
#31875000000
0&
#31937500000
1&
#32000000000
0&
#32062500000
1&
#32125000000
0&
#32187500000
1&
#32250000000
0&
#32312500000
1&
#32375000000
0&
#32437500000
1&
#32500000000
0&
#32562500000
1&
#32625000000
0&
#32687500000
1&
#32750000000
0&
#32812500000
1&
#32875000000
0&
#32937500000
1&
#33000000000
0&
#33062500000
1&
#33125000000
0&
#33187500000
1&
#33250000000
0&
#33312500000
1&
#33375000000
0&
#33437500000
1&
#33500000000
0&
#33562500000
1&
#33625000000
0&
#33687500000
1&
#33750000000
0&
#33812500000
1&
#33875000000
0&
#33937500000
1&
#34000000000
0&
#34062500000
1&
#34125000000
0&
#34187500000
1&
#34250000000
0&
#34312500000
1&
#34375000000
0&
#34437500000
1&
#34500000000
0&
#34562500000
1&
#34625000000
0&
#34687500000
1&
#34750000000
0&
#34812500000
1&
#34875000000
0&
#34937500000
1&
#35000000000
1"
0&
0'
1)
