VHDL/quadrature_decoder/previous_state_register.vhd
library ieee;
use ieee.std_logic_1164.all;

entity previous_state_register is
	port(
		A 			: in std_logic;
		B 			: in std_logic;
		prev_state 	: out std_logic_vector(1 downto 0)
	);
end previous_state_register;

architecture behav_arch of previous_state_register is
begin
	process(A,B)
	begin
		if(B'event) then
			prev_state <= A & B;
		end if;
	end process;
end behav_arch;

VHDL/quadrature_decoder/testbenches/previous_state_register_tb.vhd
library ieee;
use ieee.std_logic_1164.all;

entity previous_state_register_tb is
end previous_state_register_tb;

architecture tb_arch of previous_state_register_tb is

component previous_state_register is
	port(
		A 			: in std_logic;
		B 			: in std_logic;
		prev_state 	: out std_logic_vector(1 downto 0)
	);
end component;

for test_unit_cw : previous_state_register use entity WORK.previous_state_register(behav_arch);
for test_unit_ccw : previous_state_register use entity WORK.previous_state_register(behav_arch);

signal in_A_cw, in_B_cw, in_B_ccw : std_logic := '1';
signal in_A_ccw : std_logic := '0';
signal output_cw, output_ccw : std_logic_vector(1 downto 0);
signal clkgen : std_logic := '1';

begin

	test_unit_cw : previous_state_register port map(
		A => in_A_cw,
		B => in_B_cw,
		prev_state => output_cw
	);

	test_unit_ccw : previous_state_register port map(
		A => in_A_ccw,
		B => in_B_ccw,
		prev_state => output_ccw
	);

	-- CW signal process with T = 20 ns
	in_A_cw <= not in_A_cw after 10 ns;
	-- CCW signal process with T = 20 ns
	in_A_ccw <= not in_A_ccw after 10 ns; 
	
	clkgen <= not clkgen after 5 ns;
	process(clkgen,in_B_cw,in_B_ccw)
	begin
		if(clkgen'event and clkgen = '0') then
			in_B_cw <= not in_B_cw;
			in_B_ccw <= not in_B_ccw;
		end if;
	end process;

end tb_arch;

VHDL/quadrature_decoder/testbenches/tb_wave_forms_files/previous_state_register.vcd
$date
  Fri Jul  3 09:22:39 2020
$end
$version
  GHDL v0
$end
$timescale
  1 fs
$end
$scope module standard $end
$upscope $end
$scope module std_logic_1164 $end
$upscope $end
$scope module previous_state_register_tb $end
$var reg 1 ! in_a_cw $end
$var reg 1 " in_b_cw $end
$var reg 1 # in_b_ccw $end
$var reg 1 $ in_a_ccw $end
$var reg 2 % output_cw[1:0] $end
$var reg 2 & output_ccw[1:0] $end
$var reg 1 ' clkgen $end
$scope module test_unit_cw $end
$var reg 1 ( a $end
$var reg 1 ) b $end
$var reg 2 * prev_state[1:0] $end
$upscope $end
$scope module test_unit_ccw $end
$var reg 1 + a $end
$var reg 1 , b $end
$var reg 2 - prev_state[1:0] $end
$upscope $end
$upscope $end
$enddefinitions $end
#0
1!
1"
1#
0$
bUU %
bUU &
1'
1(
1)
bUU *
0+
1,
bUU -
#5000000
0"
0#
b10 %
b00 &
0'
0)
b10 *
0,
b00 -
#10000000
0!
1$
1'
0(
1+
#15000000
1"
1#
b01 %
b11 &
0'
1)
b01 *
1,
b11 -
#20000000
1!
0$
1'
1(
0+
#25000000
0"
0#
b10 %
b00 &
0'
0)
b10 *
0,
b00 -
#30000000
0!
1$
1'
0(
1+
#35000000
1"
1#
b01 %
b11 &
0'
1)
b01 *
1,
b11 -
#40000000
1!
0$
1'
1(
0+
#45000000
0"
0#
b10 %
b00 &
0'
0)
b10 *
0,
b00 -
#50000000
0!
1$
1'
0(
1+
#55000000
1"
1#
b01 %
b11 &
0'
1)
b01 *
1,
b11 -
#60000000
1!
0$
1'
1(
0+
#65000000
0"
0#
b10 %
b00 &
0'
0)
b10 *
0,
b00 -
#70000000
0!
1$
1'
0(
1+
#75000000
1"
1#
b01 %
b11 &
0'
1)
b01 *
1,
b11 -
#80000000
1!
0$
1'
1(
0+
#85000000
0"
0#
b10 %
b00 &
0'
0)
b10 *
0,
b00 -
#90000000
0!
1$
1'
0(
1+
#95000000
1"
1#
b01 %
b11 &
0'
1)
b01 *
1,
b11 -
#100000000
1!
0$
1'
1(
0+
