VHDL/quadrature_decoder/pulse_counter.vhd
library ieee;
use ieee.std_logic_1164.all;
use ieee.numeric_std.all;

entity pulse_counter is
	port(
		position_change : in std_logic;
		reset 			: in std_logic;
		count			: inout integer
	);
end pulse_counter;

architecture behav_arch of pulse_counter is 

	signal r_reg, r_next : integer;

begin

	process(position_change,reset)
	begin
		-- Register
		if(reset = '1') then
			r_reg <= 0;
		elsif(rising_edge(position_change)) then
			r_reg <= r_next;
		end if;
	end process;

	-- Next sate logic
	r_next <= r_reg + 1;
			
	-- Output logic
	count <= r_reg;

end behav_arch;

VHDL/quadrature_decoder/testbenches/pulse_counter_tb.vhd
library ieee;
use ieee.std_logic_1164.all;

entity pulse_counter_tb is
end pulse_counter_tb;

architecture tb_arch of pulse_counter_tb is

component pulse_counter is
	port(
		position_change : in std_logic;
		reset 			: in std_logic;
		count			: out integer
	);
end component;

signal position_change, reset : std_logic := '0';
signal count : integer;

begin

	test_unit : entity WORK.pulse_counter(behav_arch)
	port map(
		position_change => position_change,
		reset 			=> reset,
		count 			=> count
	);

	-- Position changing every 20 ns
	position_change <= not position_change after 20 ns;

	process
	begin
		wait until rising_edge(position_change);
		reset <= '1';
		wait until rising_edge(position_change);
		reset <= '0';
		wait;
	end process;

end tb_arch;

VHDL/quadrature_decoder/testbenches/tb_wave_forms_files/pulse_counter_tb.vcd
$date
  Mon Jul  6 14:08:42 2020
$end
$version
  GHDL v0
$end
$timescale
  1 fs
$end
$scope module standard $end
$upscope $end
$scope module std_logic_1164 $end
$upscope $end
$scope module numeric_std $end
$upscope $end
$scope module pulse_counter_tb $end
$var reg 1 ! position_change $end
$var reg 1 " reset $end
$var integer 32 # count $end
$scope module test_unit $end
$var reg 1 $ position_change $end
$var reg 1 % reset $end
$var integer 32 & count $end
$var integer 32 ' r_reg $end
$var integer 32 ( r_next $end
$upscope $end
$upscope $end
$enddefinitions $end
#0
0!
0"
b10000000000000000000000000000000 #
0$
0%
b10000000000000000000000000000000 &
b10000000000000000000000000000000 '
b10000000000000000000000000000001 (
#20000000
1!
1"
b0 #
1$
1%
b0 &
b0 '
b1 (
#40000000
0!
0$
#60000000
1!
0"
1$
0%
#80000000
0!
0$
#100000000
1!
b1 #
1$
b1 &
b1 '
b10 (
#120000000
0!
0$
#140000000
1!
b10 #
1$
b10 &
b10 '
b11 (
#160000000
0!
0$
#180000000
1!
b11 #
1$
b11 &
b11 '
b100 (
#200000000
0!
0$
#220000000
1!
b100 #
1$
b100 &
b100 '
b101 (
#240000000
0!
0$
#260000000
1!
b101 #
1$
b101 &
b101 '
b110 (
#280000000
0!
0$
#300000000
1!
b110 #
1$
b110 &
b110 '
b111 (
#320000000
0!
0$
#340000000
1!
b111 #
1$
b111 &
b111 '
b1000 (
#360000000
0!
0$
#380000000
1!
b1000 #
1$
b1000 &
b1000 '
b1001 (
#400000000
0!
0$
#420000000
1!
b1001 #
1$
b1001 &
b1001 '
b1010 (
#440000000
0!
0$
#460000000
1!
b1010 #
1$
b1010 &
b1010 '
b1011 (
#480000000
0!
0$
#500000000
1!
b1011 #
1$
b1011 &
b1011 '
b1100 (
#520000000
0!
0$
#540000000
1!
b1100 #
1$
b1100 &
b1100 '
b1101 (
#560000000
0!
0$
#580000000
1!
b1101 #
1$
b1101 &
b1101 '
b1110 (
#600000000
0!
0$
#620000000
1!
b1110 #
1$
b1110 &
b1110 '
b1111 (
#640000000
0!
0$
#660000000
1!
b1111 #
1$
b1111 &
b1111 '
b10000 (
#680000000
0!
0$
#700000000
1!
b10000 #
1$
b10000 &
b10000 '
b10001 (
#720000000
0!
0$
#740000000
1!
b10001 #
1$
b10001 &
b10001 '
b10010 (
#760000000
0!
0$
#780000000
1!
b10010 #
1$
b10010 &
b10010 '
b10011 (
#800000000
0!
0$
#820000000
1!
b10011 #
1$
b10011 &
b10011 '
b10100 (
#840000000
0!
0$
#860000000
1!
b10100 #
1$
b10100 &
b10100 '
b10101 (
#880000000
0!
0$
#900000000
1!
b10101 #
1$
b10101 &
b10101 '
b10110 (
#920000000
0!
0$
#940000000
1!
b10110 #
1$
b10110 &
b10110 '
b10111 (
#960000000
0!
0$
#980000000
1!
b10111 #
1$
b10111 &
b10111 '
b11000 (
#1000000000
0!
0$
