VHDL/quadrature_decoder/change_detector.vhd
library ieee;
use ieee.std_logic_1164.all;

entity change_detector is
	port(
		position			: in std_logic_vector(12 downto 0);
		clk					: in std_logic;
		reset 				: in std_logic;
		position_change 	: out std_logic
	);
end change_detector;

architecture two_stage_arch of change_detector is

signal r_reg, r_next : std_logic_vector(position'high downto 0);

begin
	-- Register
	process(reset,clk)
	begin
		if (reset = '1') then
			r_reg <= (others => '0');
		elsif(rising_edge(clk)) then
			r_reg <= r_next;
		end if;
	end process;

	-- Next state logic
	r_next <= position;

	-- Output Logic
	position_change <= '1' when (position /= r_reg) else '0';
end two_stage_arch;

VHDL/quadrature_decoder/pulse_counter.vhd
library ieee;
use ieee.std_logic_1164.all;
use ieee.numeric_std.all;

entity pulse_counter is
	port(
		position_change : in std_logic;
		reset 			: in std_logic;
		count			: inout integer
	);
end pulse_counter;

architecture behav_arch of pulse_counter is 

	signal r_reg, r_next : integer;

begin

	process(position_change,reset)
	begin
		-- Register
		if(reset = '1') then
			r_reg <= 0;
		elsif(rising_edge(position_change)) then
			r_reg <= r_next;
		end if;
	end process;

	-- Next sate logic
	r_next <= r_reg + 1;
			
	-- Output logic
	count <= r_reg;

end behav_arch;

VHDL/quadrature_decoder/neg_edge_detector.vhd
library ieee;
use ieee.std_logic_1164.all;

entity neg_edge_detector is
	port (
		i_clk	: in  std_logic;
		i_rstb	: in  std_logic;
		i_input	: in  std_logic;
		o_pulse	: out std_logic
	);
end neg_edge_detector;

architecture rtl of neg_edge_detector is

signal r0_input	: std_logic;
signal r1_input	: std_logic;

begin

p_rising_edge_detector : process(i_clk,i_rstb)
begin
	if(i_rstb='1') then
	    r0_input <= '0';
	    r1_input <= '0';
  	elsif(i_clk'event) then
	    r0_input <= i_input;
	    r1_input <= r0_input;
  	end if;
end process p_rising_edge_detector;

o_pulse <= not r0_input and r1_input;

end rtl;

VHDL/quadrature_decoder/clk_timer.vhd
library ieee;
use ieee.std_logic_1164.all;
use ieee.numeric_std.all;
 
entity clk_timer is
	generic(timer_threshold_cycles : integer);
	port(
	    clk 		: in std_logic;
	    reset		: in std_logic;
	    timer 		: out std_logic
    );
end entity;
 
architecture rtl of clk_timer is
 
    -- Signal for counting clock periods
    signal r_reg, r_next : integer;
 
begin

    -- Register
    process(clk) is
    begin
        if(reset = '1') then
            r_reg <= 0;
        elsif(rising_edge(clk)) then
            r_reg <= r_next;
        end if;
    end process;

    -- Next state logic
    r_next <= 0 when (r_reg = timer_threshold_cycles - 1)
                else r_reg + 1;

    -- Output logic
    timer <= '1' when (r_reg = timer_threshold_cycles - 1)
                else '0';
 
end architecture;

VHDL/quadrature_decoder/speed_computer.vhd
library ieee;
use ieee.std_logic_1164.all;
use ieee.numeric_std.all;

entity speed_computer is
	generic(timer_threshold_cycles : integer);
	port(
		clk 			: in std_logic;
		position_change : in std_logic;
		global_reset	: in std_logic;
		speed 			: out integer
	);
end speed_computer;

architecture struct_arch of speed_computer is

-- Clock Timer
component clk_timer is
	generic(timer_threshold_cycles : integer);
	port(
	    clk 		: in std_logic;
	    reset		: in std_logic;
	    timer 		: out std_logic
    );
end component;

-- Pulse Counter
component pulse_counter is
	port(
		position_change : in std_logic;
		reset 			: in std_logic;
		count			: inout integer
	);
end component;

-- Negative Edge Detector
component neg_edge_detector is
	port (
		i_clk	: in  std_logic;
		i_rstb	: in  std_logic;
		i_input	: in  std_logic;
		o_pulse	: out std_logic
	);
end component;

signal timer_pulse, timer_pulse_neg_edge : std_logic;
signal count : integer;
signal clk_timer_reset, pulse_counter_reset : std_logic;
signal r_reg, r_next : integer;

begin

	U1 : entity WORK.clk_timer(rtl)
	generic map (timer_threshold_cycles => timer_threshold_cycles)
	port map(
	    clk 	=> clk,
	    reset	=> clk_timer_reset,
	    timer 	=> timer_pulse
	);

	U2 : entity WORK.neg_edge_detector(rtl)
	port map(
		i_clk	=> clk,
		i_rstb	=> global_reset,
		i_input	=> timer_pulse,
		o_pulse	=> timer_pulse_neg_edge
	);

	U3 : entity WORK.pulse_counter(behav_arch)
	port map(
		position_change => position_change,
		reset 			=> pulse_counter_reset,
		count			=> count
	);

	-- Resets to clk_timer and pulse_counter.
	clk_timer_reset <= global_reset or timer_pulse;
	pulse_counter_reset <= global_reset or timer_pulse_neg_edge;

	-- Register
	process(global_reset,timer_pulse)
	begin
		if(global_reset = '1') then
			r_reg <= 0;
		elsif(rising_edge(timer_pulse)) then
			r_reg <= r_next;
		else
		end if;
	end process;

	-- Next State Logic
	r_next <= count;

	-- Output Logic
	speed <= r_reg;


end struct_arch;

VHDL/quadrature_decoder/dir_pos_computer.vhd
library ieee;
use ieee.std_logic_1164.all;
use ieee.numeric_std.all;

entity dir_pos_computer is
	port(
		A 				: in std_logic;
		B 				: in std_logic;
		reset			: in std_logic;
		direction		: out std_logic;
		position		: out std_logic_vector(12 downto 0)
	);
end dir_pos_computer;

architecture behav_arch of dir_pos_computer is

type state_type is (S0,S1,S2,S3); -- machine states
signal state : state_type;
signal dir : std_logic;
signal count : signed(12 downto 0);

begin
	process(A,B) -- State Machine Process
		variable wave : std_logic_vector(1 downto 0);
	begin
		if (reset = '1') then
			state <= S0;
			dir <= '1';
			count <= (others => '0');
		elsif (A'event or B'event) then
			wave := A&B;

			case state is
				when S0 =>
					if (wave = "01") then
						State <= S1;
						dir <= '1';
						count <= count + 1;
					elsif (wave = "10") then
						State <= S2;
						dir <= '0';
						count <= count - 1;
					end if;

				when S1 =>
					if (wave = "11") then
						State <= S3;
						dir <= '1';
						count <= count + 1;
					elsif (wave = "00") then
						State <= S0;
						dir <= '0';
						count <= count - 1;
					end if;

				when S2 =>
					if (wave = "00") then
						State <= S0;
						dir <= '1';
						count <= count + 1;
					elsif (wave = "11") then
						State <= S3;
						dir <= '0';
						count <= count - 1;
					end if;

				when S3 =>
					if (wave = "10") then
						State <= S2;
						dir <= '1';
						count <= count + 1;
					elsif (wave = "01") then
						State <= S1;
						dir <= '0';
						count <= count - 1;
					end if;
			end case;
		end if;
	end process;

	-- Output logic
	position <= std_logic_vector(count);
	direction <= dir;

end behav_arch;

VHDL/quadrature_decoder/quadrature_decoder.vhd
library ieee;
use ieee.std_logic_1164.all;

entity quadrature_decoder is
	generic(timer_threshold_cycles : integer);
	port(
		A 			: in 	std_logic;
		B 			: in 	std_logic;
		Z 			: in 	std_logic;
		clk 		: in 	std_logic;
		reset 		: in 	std_logic;
		position	: inout	std_logic_vector(12 downto 0);
		direction	: out 	std_logic;
		speed		: out	integer
	);
end quadrature_decoder;

architecture struct_arch of quadrature_decoder is

	-- Direction and position Computer
	component dir_pos_computer is
		port(
			A 				: in std_logic;
			B 				: in std_logic;
			reset			: in std_logic;
			direction		: out std_logic;
			position		: out std_logic_vector(12 downto 0)
		);
	end component;

	-- Change in position detector
	component change_detector is
		port(
			position			: in std_logic_vector(12 downto 0);
			clk					: in std_logic;
			reset 				: in std_logic;
			position_change 	: out std_logic
		);
	end component;

	-- Speed computer
	component speed_computer is
		generic(timer_threshold_cycles : integer);
		port(
			clk 			: in std_logic;
			position_change : in std_logic;
			global_reset	: in std_logic;
			speed 			: out integer
		);
	end component;

	-- Signals
	signal position_change : std_logic;
	signal dir_pos_computer_reset : std_logic;

begin

	-- Direction and Position computer
	U1 : entity WORK.dir_pos_computer(behav_arch)
	port map(
		A => A,
		B => B,
		reset => reset,
		direction => direction,
		position => position
	);

	-- Speed computer
	U2 : entity WORK.speed_computer(struct_arch)
	generic map(timer_threshold_cycles => timer_threshold_cycles)
	port map(
		clk => clk,
		position_change => position_change,
		global_reset => reset,
		speed => speed
	);

		-- Change in position detector
	U3 : entity WORK.change_detector(two_stage_arch)
	port map(
		position => position,
		clk => clk,
		reset => reset,
		position_change => position_change
	);

end struct_arch;

VHDL/quadrature_decoder/testbenches/quadrature_decoder_tb.vhd
library ieee;
use ieee.std_logic_1164.all;

entity quadrature_decoder_tb is
end quadrature_decoder_tb;

architecture tb_arch of quadrature_decoder_tb is

	component quadrature_decoder is
		generic(timer_threshold_cycles : integer);
		port(
			A 			: in 	std_logic;
			B 			: in 	std_logic;
			Z 			: in 	std_logic;
			clk 		: in 	std_logic;
			reset 		: in 	std_logic;
			position	: inout	std_logic_vector(12 downto 0);
			direction	: out 	std_logic;
			speed		: out	integer
		);
	end component;

	constant ClockFrequencyHz 			: integer := 16000000; -- 16 MHz
    constant ClockPeriod      			: time := 1000 ms / ClockFrequencyHz;
    constant timer_threshold_cycles		: integer := ClockFrequencyHz / 1000; -- Clk cycles per mili-second (10^-3)

    -- Signals
    signal in_A, in_B, in_Z : std_logic := '0';
    signal global_clk 		: std_logic := '0';
    signal global_reset		: std_logic := '1';
    signal position			: std_logic_vector(12 downto 0);
    signal direction		: std_logic;
    signal speed			: integer;

    signal clkgen1,clkgen2,clkgen3,clkgen2_inv : std_logic := '0';
    signal trigger			: integer := 0;

begin

	-- DUT
	test_unit : entity WORK.quadrature_decoder(struct_arch)
	generic map(timer_threshold_cycles => timer_threshold_cycles)
	port map(
		A 			=> in_A,
		B 			=> in_B,
		Z 			=> in_Z,
		clk 		=> global_clk,
		reset 		=> global_reset,
		position	=> position,
		direction	=> direction,
		speed		=> speed
	);

	-- Global clock process
	global_clk <= not global_clk after ClockPeriod/2;

	-- ASSUMPTIONS
	-- Encoder has a resolution of 2048 PPR
	-- Global clock frequency is 16MHz

	-- TEST 1: DIRECTION, POSITION, AND SPEED

	global_reset <= '0' after ClockPeriod*4;

	clkgen1 <= not clkgen1 after ClockPeriod*200;
	clkgen2 <= not clkgen2 after ClockPeriod*50;
	clkgen3 <= not clkgen3 after ClockPeriod*100;

	clkgen2_inv <= not clkgen2;

	-- Trigger used for different rotations
	process
	begin
		wait for ClockPeriod*20000;
		trigger <= 1;
		wait for ClockPeriod*5000;
		trigger <= 2;
		wait for ClockPeriod*10000;
		trigger <= 3;
	end process;

	p_channel_B : process(clkgen1,clkgen2,clkgen3,in_B) is
	begin
		-- Rotate CW for 1/4 revolutions at 10dps
		if(trigger = 0) then
			if(rising_edge(clkgen1)) then
				in_B <= not in_B;
			end if;
		-- Rotate CCW for 1/2 revolutions at 50dps
		elsif(trigger = 1) then
			if(rising_edge(clkgen2)) then
				in_B <= not in_B;
			end if;
		-- Rotate CW for 1/4 revolutions at 5dps
		elsif(trigger = 2) then
			if(rising_edge(clkgen3)) then
				in_B <= not in_B;
			end if;
		else
		end if;
	end process p_channel_B;

	p_channel_A : process(clkgen1,clkgen2,clkgen3,clkgen2_inv,in_A) is
	begin
		-- Rotate CW for 1/4 revolutions at 10dps
		if(trigger = 0) then
			if(falling_edge(clkgen1)) then
				in_A <= not in_A;
			end if;
		-- Rotate CCW for 1/2 revolutions at 50dps
		elsif(trigger = 1) then
			if(rising_edge(clkgen2_inv)) then
				in_A <= not in_A;
			end if;
		-- Rotate CW for 1/4 revolutions at 5dps
		elsif(trigger = 2) then
			if(falling_edge(clkgen3)) then
				in_A <= not in_A;
			end if;
		else
		end if;
	end process p_channel_A;

	p_channel_Z : process(position,in_A) is
	begin
		if(position'event and position = "0000000110000") then
			in_Z <= '1';
		else
			in_Z <= '0';
		end if;
	end process p_channel_Z;

end tb_arch;

VHDL/quadrature_decoder/testbenches/tb_wave_forms_files/quadrature_encoder_tb.vcd
$date
  Tue Jul  7 11:16:32 2020
$end
$version
  GHDL v0
$end
$timescale
  1 fs
$end
$scope module standard $end
$upscope $end
$scope module std_logic_1164 $end
$upscope $end
$scope module numeric_std $end
$upscope $end
$scope module quadrature_decoder_tb $end
$var reg 1 ! in_a $end
$var reg 1 " in_b $end
$var reg 1 # in_z $end
$var reg 1 $ global_clk $end
$var reg 1 % global_reset $end
$var reg 13 & position[12:0] $end
$var reg 1 ' direction $end
$var integer 32 ( speed $end
$var reg 1 ) clkgen1 $end
$var reg 1 * clkgen2 $end
$var reg 1 + clkgen3 $end
$var reg 1 , clkgen2_inv $end
$var integer 32 - trigger $end
$scope module test_unit $end
$var reg 1 . a $end
$var reg 1 / b $end
$var reg 1 0 z $end
$var reg 1 1 clk $end
$var reg 1 2 reset $end
$var reg 13 3 position[12:0] $end
$var reg 1 4 direction $end
$var integer 32 5 speed $end
$var reg 1 6 position_change $end
$var reg 1 7 dir_pos_computer_reset $end
$scope module u1 $end
$var reg 1 8 a $end
$var reg 1 9 b $end
$var reg 1 : reset $end
$var reg 1 ; direction $end
$var reg 13 < position[12:0] $end
$comment state is not handled $end
$var reg 1 = dir $end
$var reg 13 > count[12:0] $end
$upscope $end
$scope module u2 $end
$var reg 1 ? clk $end
$var reg 1 @ position_change $end
$var reg 1 A global_reset $end
$var integer 32 B speed $end
$var reg 1 C timer_pulse $end
$var reg 1 D timer_pulse_neg_edge $end
$var integer 32 E count $end
$var reg 1 F clk_timer_reset $end
$var reg 1 G pulse_counter_reset $end
$var integer 32 H r_reg $end
$var integer 32 I r_next $end
$scope module u1 $end
$var reg 1 J clk $end
$var reg 1 K reset $end
$var reg 1 L timer $end
$var integer 32 M r_reg $end
$var integer 32 N r_next $end
$upscope $end
$scope module u2 $end
$var reg 1 O i_clk $end
$var reg 1 P i_rstb $end
$var reg 1 Q i_input $end
$var reg 1 R o_pulse $end
$var reg 1 S r0_input $end
$var reg 1 T r1_input $end
$upscope $end
$scope module u3 $end
$var reg 1 U position_change $end
$var reg 1 V reset $end
$var integer 32 W count $end
$var integer 32 X r_reg $end
$var integer 32 Y r_next $end
$upscope $end
$upscope $end
$scope module u3 $end
$var reg 13 Z position[12:0] $end
$var reg 1 [ clk $end
$var reg 1 \ reset $end
$var reg 1 ] position_change $end
$var reg 13 ^ r_reg[12:0] $end
$var reg 13 _ r_next[12:0] $end
$upscope $end
$upscope $end
$upscope $end
$enddefinitions $end
#0
0!
0"
0#
0$
1%
b0000000000000 &
1'
b0 (
0)
0*
0+
1,
b0 -
0.
0/
00
01
12
b0000000000000 3
14
b0 5
06
U7
08
09
1:
1;
b0000000000000 <
1=
b0000000000000 >
0?
0@
1A
b0 B
0C
0D
b0 E
1F
1G
b0 H
b0 I
0J
1K
0L
b10000000000000000000000000000000 M
b10000000000000000000000000000001 N
0O
1P
0Q
0R
0S
0T
0U
1V
b0 W
b0 X
b1 Y
b0000000000000 Z
0[
1\
0]
b0000000000000 ^
b0000000000000 _
#31250000
1$
11
1?
1J
b0 M
b1 N
1O
1[
#62500000
0$
01
0?
0J
0O
0[
#93750000
1$
11
1?
1J
1O
1[
#125000000
0$
01
0?
0J
0O
0[
#156250000
1$
11
1?
1J
1O
1[
#187500000
0$
01
0?
0J
0O
0[
#218750000
1$
11
1?
1J
1O
1[
#250000000
0$
0%
01
02
0:
0?
0A
0F
0G
0J
0K
0O
0P
0V
0[
0\
#281250000
1$
11
1?
1J
b1 M
b10 N
1O
1[
#312500000
0$
01
0?
0J
0O
0[
#343750000
1$
11
1?
1J
b10 M
b11 N
1O
1[
#375000000
0$
01
0?
0J
0O
0[
#406250000
1$
11
1?
1J
b11 M
b100 N
1O
1[
#437500000
0$
01
0?
0J
0O
0[
#468750000
1$
11
1?
1J
b100 M
b101 N
1O
1[
#500000000
0$
01
0?
0J
0O
0[
#531250000
1$
11
1?
1J
b101 M
b110 N
1O
1[
#562500000
0$
01
0?
0J
0O
0[
#593750000
1$
11
1?
1J
b110 M
b111 N
1O
1[
#625000000
0$
01
0?
0J
0O
0[
#656250000
1$
11
1?
1J
b111 M
b1000 N
1O
1[
#687500000
0$
01
0?
0J
0O
0[
#718750000
1$
11
1?
1J
b1000 M
b1001 N
1O
1[
#750000000
0$
01
0?
0J
0O
0[
#781250000
1$
11
1?
1J
b1001 M
b1010 N
1O
1[
#812500000
0$
01
0?
0J
0O
0[
#843750000
1$
11
1?
1J
b1010 M
b1011 N
1O
1[
#875000000
0$
01
0?
0J
0O
0[
#906250000
1$
11
1?
1J
b1011 M
b1100 N
1O
1[
#937500000
0$
01
0?
0J
0O
0[
#968750000
1$
11
1?
1J
b1100 M
b1101 N
1O
1[
#1000000000
0$
01
0?
0J
0O
0[
#1031250000
1$
11
1?
1J
b1101 M
b1110 N
1O
1[
#1062500000
0$
01
0?
0J
0O
0[
#1093750000
1$
11
1?
1J
b1110 M
b1111 N
1O
1[
#1125000000
0$
01
0?
0J
0O
0[
#1156250000
1$
11
1?
1J
b1111 M
b10000 N
1O
1[
#1187500000
0$
01
0?
0J
0O
0[
#1218750000
1$
11
1?
1J
b10000 M
b10001 N
1O
1[
#1250000000
0$
01
0?
0J
0O
0[
#1281250000
1$
11
1?
1J
b10001 M
b10010 N
1O
1[
#1312500000
0$
01
0?
0J
0O
0[
#1343750000
1$
11
1?
1J
b10010 M
b10011 N
1O
1[
#1375000000
0$
01
0?
0J
0O
0[
#1406250000
1$
11
1?
1J
b10011 M
b10100 N
1O
1[
#1437500000
0$
01
0?
0J
0O
0[
#1468750000
1$
11
1?
1J
b10100 M
b10101 N
1O
1[
#1500000000
0$
01
0?
0J
0O
0[
#1531250000
1$
11
1?
1J
b10101 M
b10110 N
1O
1[
#1562500000
0$
01
0?
0J
0O
0[
#1593750000
1$
11
1?
1J
b10110 M
b10111 N
1O
1[
#1625000000
0$
01
0?
0J
0O
0[
#1656250000
1$
11
1?
1J
b10111 M
b11000 N
1O
1[
#1687500000
0$
01
0?
0J
0O
0[
#1718750000
1$
11
1?
1J
b11000 M
b11001 N
1O
1[
#1750000000
0$
01
0?
0J
0O
0[
#1781250000
1$
11
1?
1J
b11001 M
b11010 N
1O
1[
#1812500000
0$
01
0?
0J
0O
0[
#1843750000
1$
11
1?
1J
b11010 M
b11011 N
1O
1[
#1875000000
0$
01
0?
0J
0O
0[
#1906250000
1$
11
1?
1J
b11011 M
b11100 N
1O
1[
#1937500000
0$
01
0?
0J
0O
0[
#1968750000
1$
11
1?
1J
b11100 M
b11101 N
1O
1[
#2000000000
0$
01
0?
0J
0O
0[
#2031250000
1$
11
1?
1J
b11101 M
b11110 N
1O
1[
#2062500000
0$
01
0?
0J
0O
0[
#2093750000
1$
11
1?
1J
b11110 M
b11111 N
1O
1[
#2125000000
0$
01
0?
0J
0O
0[
#2156250000
1$
11
1?
1J
b11111 M
b100000 N
1O
1[
#2187500000
0$
01
0?
0J
0O
0[
#2218750000
1$
11
1?
1J
b100000 M
b100001 N
1O
1[
#2250000000
0$
01
0?
0J
0O
0[
#2281250000
1$
11
1?
1J
b100001 M
b100010 N
1O
1[
#2312500000
0$
01
0?
0J
0O
0[
#2343750000
1$
11
1?
1J
b100010 M
b100011 N
1O
1[
#2375000000
0$
01
0?
0J
0O
0[
#2406250000
1$
11
1?
1J
b100011 M
b100100 N
1O
1[
#2437500000
0$
01
0?
0J
0O
0[
#2468750000
1$
11
1?
1J
b100100 M
b100101 N
1O
1[
#2500000000
0$
01
0?
0J
0O
0[
#2531250000
1$
11
1?
1J
b100101 M
b100110 N
1O
1[
#2562500000
0$
01
0?
0J
0O
0[
#2593750000
1$
11
1?
1J
b100110 M
b100111 N
1O
1[
#2625000000
0$
01
0?
0J
0O
0[
#2656250000
1$
11
1?
1J
b100111 M
b101000 N
1O
1[
#2687500000
0$
01
0?
0J
0O
0[
#2718750000
1$
11
1?
1J
b101000 M
b101001 N
1O
1[
#2750000000
0$
01
0?
0J
0O
0[
#2781250000
1$
11
1?
1J
b101001 M
b101010 N
1O
1[
#2812500000
0$
01
0?
0J
0O
0[
#2843750000
1$
11
1?
1J
b101010 M
b101011 N
1O
1[
#2875000000
0$
01
0?
0J
0O
0[
#2906250000
1$
11
1?
1J
b101011 M
b101100 N
1O
1[
#2937500000
0$
01
0?
0J
0O
0[
#2968750000
1$
11
1?
1J
b101100 M
b101101 N
1O
1[
#3000000000
0$
01
0?
0J
0O
0[
#3031250000
1$
11
1?
1J
b101101 M
b101110 N
1O
1[
#3062500000
0$
01
0?
0J
0O
0[
#3093750000
1$
11
1?
1J
b101110 M
b101111 N
1O
1[
#3125000000
0$
1*
0,
01
0?
0J
0O
0[
#3156250000
1$
11
1?
1J
b101111 M
b110000 N
1O
1[
#3187500000
0$
01
0?
0J
0O
0[
#3218750000
1$
11
1?
1J
b110000 M
b110001 N
1O
1[
#3250000000
0$
01
0?
0J
0O
0[
#3281250000
1$
11
1?
1J
b110001 M
b110010 N
1O
1[
#3312500000
0$
01
0?
0J
0O
0[
#3343750000
1$
11
1?
1J
b110010 M
b110011 N
1O
1[
#3375000000
0$
01
0?
0J
0O
0[
#3406250000
1$
11
1?
1J
b110011 M
b110100 N
1O
1[
#3437500000
0$
01
0?
0J
0O
0[
#3468750000
1$
11
1?
1J
b110100 M
b110101 N
1O
1[
#3500000000
0$
01
0?
0J
0O
0[
#3531250000
1$
11
1?
1J
b110101 M
b110110 N
1O
1[
#3562500000
0$
01
0?
0J
0O
0[
#3593750000
1$
11
1?
1J
b110110 M
b110111 N
1O
1[
#3625000000
0$
01
0?
0J
0O
0[
#3656250000
1$
11
1?
1J
b110111 M
b111000 N
1O
1[
#3687500000
0$
01
0?
0J
0O
0[
#3718750000
1$
11
1?
1J
b111000 M
b111001 N
1O
1[
#3750000000
0$
01
0?
0J
0O
0[
#3781250000
1$
11
1?
1J
b111001 M
b111010 N
1O
1[
#3812500000
0$
01
0?
0J
0O
0[
#3843750000
1$
11
1?
1J
b111010 M
b111011 N
1O
1[
#3875000000
0$
01
0?
0J
0O
0[
#3906250000
1$
11
1?
1J
b111011 M
b111100 N
1O
1[
#3937500000
0$
01
0?
0J
0O
0[
#3968750000
1$
11
1?
1J
b111100 M
b111101 N
1O
1[
#4000000000
0$
01
0?
0J
0O
0[
#4031250000
1$
11
1?
1J
b111101 M
b111110 N
1O
1[
#4062500000
0$
01
0?
0J
0O
0[
#4093750000
1$
11
1?
1J
b111110 M
b111111 N
1O
1[
#4125000000
0$
01
0?
0J
0O
0[
#4156250000
1$
11
1?
1J
b111111 M
b1000000 N
1O
1[
#4187500000
0$
01
0?
0J
0O
0[
#4218750000
1$
11
1?
1J
b1000000 M
b1000001 N
1O
1[
#4250000000
0$
01
0?
0J
0O
0[
#4281250000
1$
11
1?
1J
b1000001 M
b1000010 N
1O
1[
#4312500000
0$
01
0?
0J
0O
0[
#4343750000
1$
11
1?
1J
b1000010 M
b1000011 N
1O
1[
#4375000000
0$
01
0?
0J
0O
0[
#4406250000
1$
11
1?
1J
b1000011 M
b1000100 N
1O
1[
#4437500000
0$
01
0?
0J
0O
0[
#4468750000
1$
11
1?
1J
b1000100 M
b1000101 N
1O
1[
#4500000000
0$
01
0?
0J
0O
0[
#4531250000
1$
11
1?
1J
b1000101 M
b1000110 N
1O
1[
#4562500000
0$
01
0?
0J
0O
0[
#4593750000
1$
11
1?
1J
b1000110 M
b1000111 N
1O
1[
#4625000000
0$
01
0?
0J
0O
0[
#4656250000
1$
11
1?
1J
b1000111 M
b1001000 N
1O
1[
#4687500000
0$
01
0?
0J
0O
0[
#4718750000
1$
11
1?
1J
b1001000 M
b1001001 N
1O
1[
#4750000000
0$
01
0?
0J
0O
0[
#4781250000
1$
11
1?
1J
b1001001 M
b1001010 N
1O
1[
#4812500000
0$
01
0?
0J
0O
0[
#4843750000
1$
11
1?
1J
b1001010 M
b1001011 N
1O
1[
#4875000000
0$
01
0?
0J
0O
0[
#4906250000
1$
11
1?
1J
b1001011 M
b1001100 N
1O
1[
#4937500000
0$
01
0?
0J
0O
0[
#4968750000
1$
11
1?
1J
b1001100 M
b1001101 N
1O
1[
#5000000000
0$
01
0?
0J
0O
0[
#5031250000
1$
11
1?
1J
b1001101 M
b1001110 N
1O
1[
#5062500000
0$
01
0?
0J
0O
0[
#5093750000
1$
11
1?
1J
b1001110 M
b1001111 N
1O
1[
#5125000000
0$
01
0?
0J
0O
0[
#5156250000
1$
11
1?
1J
b1001111 M
b1010000 N
1O
1[
#5187500000
0$
01
0?
0J
0O
0[
#5218750000
1$
11
1?
1J
b1010000 M
b1010001 N
1O
1[
#5250000000
0$
01
0?
0J
0O
0[
#5281250000
1$
11
1?
1J
b1010001 M
b1010010 N
1O
1[
#5312500000
0$
01
0?
0J
0O
0[
#5343750000
1$
11
1?
1J
b1010010 M
b1010011 N
1O
1[
#5375000000
0$
01
0?
0J
0O
0[
#5406250000
1$
11
1?
1J
b1010011 M
b1010100 N
1O
1[
#5437500000
0$
01
0?
0J
0O
0[
#5468750000
1$
11
1?
1J
b1010100 M
b1010101 N
1O
1[
#5500000000
0$
01
0?
0J
0O
0[
#5531250000
1$
11
1?
1J
b1010101 M
b1010110 N
1O
1[
#5562500000
0$
01
0?
0J
0O
0[
#5593750000
1$
11
1?
1J
b1010110 M
b1010111 N
1O
1[
#5625000000
0$
01
0?
0J
0O
0[
#5656250000
1$
11
1?
1J
b1010111 M
b1011000 N
1O
1[
#5687500000
0$
01
0?
0J
0O
0[
#5718750000
1$
11
1?
1J
b1011000 M
b1011001 N
1O
1[
#5750000000
0$
01
0?
0J
0O
0[
#5781250000
1$
11
1?
1J
b1011001 M
b1011010 N
1O
1[
#5812500000
0$
01
0?
0J
0O
0[
#5843750000
1$
11
1?
1J
b1011010 M
b1011011 N
1O
1[
#5875000000
0$
01
0?
0J
0O
0[
#5906250000
1$
11
1?
1J
b1011011 M
b1011100 N
1O
1[
#5937500000
0$
01
0?
0J
0O
0[
#5968750000
1$
11
1?
1J
b1011100 M
b1011101 N
1O
1[
#6000000000
0$
01
0?
0J
0O
0[
#6031250000
1$
11
1?
1J
b1011101 M
b1011110 N
1O
1[
#6062500000
0$
01
0?
0J
0O
0[
#6093750000
1$
11
1?
1J
b1011110 M
b1011111 N
1O
1[
#6125000000
0$
01
0?
0J
0O
0[
#6156250000
1$
11
1?
1J
b1011111 M
b1100000 N
1O
1[
#6187500000
0$
01
0?
0J
0O
0[
#6218750000
1$
11
1?
1J
b1100000 M
b1100001 N
1O
1[
#6250000000
0$
0*
1+
1,
01
0?
0J
0O
0[
#6281250000
1$
11
1?
1J
b1100001 M
b1100010 N
1O
1[
#6312500000
0$
01
0?
0J
0O
0[
#6343750000
1$
11
1?
1J
b1100010 M
b1100011 N
1O
1[
#6375000000
0$
01
0?
0J
0O
0[
#6406250000
1$
11
1?
1J
b1100011 M
b1100100 N
1O
1[
#6437500000
0$
01
0?
0J
0O
0[
#6468750000
1$
11
1?
1J
b1100100 M
b1100101 N
1O
1[
#6500000000
0$
01
0?
0J
0O
0[
#6531250000
1$
11
1?
1J
b1100101 M
b1100110 N
1O
1[
#6562500000
0$
01
0?
0J
0O
0[
#6593750000
1$
11
1?
1J
b1100110 M
b1100111 N
1O
1[
#6625000000
0$
01
0?
0J
0O
0[
#6656250000
1$
11
1?
1J
b1100111 M
b1101000 N
1O
1[
#6687500000
0$
01
0?
0J
0O
0[
#6718750000
1$
11
1?
1J
b1101000 M
b1101001 N
1O
1[
#6750000000
0$
01
0?
0J
0O
0[
#6781250000
1$
11
1?
1J
b1101001 M
b1101010 N
1O
1[
#6812500000
0$
01
0?
0J
0O
0[
#6843750000
1$
11
1?
1J
b1101010 M
b1101011 N
1O
1[
#6875000000
0$
01
0?
0J
0O
0[
#6906250000
1$
11
1?
1J
b1101011 M
b1101100 N
1O
1[
#6937500000
0$
01
0?
0J
0O
0[
#6968750000
1$
11
1?
1J
b1101100 M
b1101101 N
1O
1[
#7000000000
0$
01
0?
0J
0O
0[
#7031250000
1$
11
1?
1J
b1101101 M
b1101110 N
1O
1[
#7062500000
0$
01
0?
0J
0O
0[
#7093750000
1$
11
1?
1J
b1101110 M
b1101111 N
1O
1[
#7125000000
0$
01
0?
0J
0O
0[
#7156250000
1$
11
1?
1J
b1101111 M
b1110000 N
1O
1[
#7187500000
0$
01
0?
0J
0O
0[
#7218750000
1$
11
1?
1J
b1110000 M
b1110001 N
1O
1[
#7250000000
0$
01
0?
0J
0O
0[
#7281250000
1$
11
1?
1J
b1110001 M
b1110010 N
1O
1[
#7312500000
0$
01
0?
0J
0O
0[
#7343750000
1$
11
1?
1J
b1110010 M
b1110011 N
1O
1[
#7375000000
0$
01
0?
0J
0O
0[
#7406250000
1$
11
1?
1J
b1110011 M
b1110100 N
1O
1[
#7437500000
0$
01
0?
0J
0O
0[
#7468750000
1$
11
1?
1J
b1110100 M
b1110101 N
1O
1[
#7500000000
0$
01
0?
0J
0O
0[
#7531250000
1$
11
1?
1J
b1110101 M
b1110110 N
1O
1[
#7562500000
0$
01
0?
0J
0O
0[
#7593750000
1$
11
1?
1J
b1110110 M
b1110111 N
1O
1[
#7625000000
0$
01
0?
0J
0O
0[
#7656250000
1$
11
1?
1J
b1110111 M
b1111000 N
1O
1[
#7687500000
0$
01
0?
0J
0O
0[
#7718750000
1$
11
1?
1J
b1111000 M
b1111001 N
1O
1[
#7750000000
0$
01
0?
0J
0O
0[
#7781250000
1$
11
1?
1J
b1111001 M
b1111010 N
1O
1[
#7812500000
0$
01
0?
0J
0O
0[
#7843750000
1$
11
1?
1J
b1111010 M
b1111011 N
1O
1[
#7875000000
0$
01
0?
0J
0O
0[
#7906250000
1$
11
1?
1J
b1111011 M
b1111100 N
1O
1[
#7937500000
0$
01
0?
0J
0O
0[
#7968750000
1$
11
1?
1J
b1111100 M
b1111101 N
1O
1[
#8000000000
0$
01
0?
0J
0O
0[
#8031250000
1$
11
1?
1J
b1111101 M
b1111110 N
1O
1[
#8062500000
0$
01
0?
0J
0O
0[
#8093750000
1$
11
1?
1J
b1111110 M
b1111111 N
1O
1[
#8125000000
0$
01
0?
0J
0O
0[
#8156250000
1$
11
1?
1J
b1111111 M
b10000000 N
1O
1[
#8187500000
0$
01
0?
0J
0O
0[
#8218750000
1$
11
1?
1J
b10000000 M
b10000001 N
1O
1[
#8250000000
0$
01
0?
0J
0O
0[
#8281250000
1$
11
1?
1J
b10000001 M
b10000010 N
1O
1[
